[
  {
    "Plaza Code": 15001,
    "Plaza Name": "Pantangi",
    "Conc. Type": "Conc.",
    "Plaza Type": "TOLL",
    "Plaza Sub Type": "NATIONAL",
    "Sate": "Telangana",
    "City": "Nalgonda",
    "Conc. name": "GMR",
    "Latitude": 17.232887,
    "Longitude": 78.960464
  },
  {
    "Plaza Code": 15002,
    "Plaza Name": "Koralaphad",
    "Conc. Type": "Conc.",
    "Plaza Type": "TOLL",
    "Plaza Sub Type": "NATIONAL",
    "Sate": "Telangana",
    "City": "Nalgonda",
    "Conc. name": "GMR",
    "Latitude": 17.159784,
    "Longitude": 79.475426
  },
  {
    "Plaza Code": 16001,
    "Plaza Name": "Vanagiri",
    "Conc. Type": "Conc.",
    "Plaza Type": "TOLL",
    "Plaza Sub Type": "NATIONAL",
    "Sate": "Karnataka",
    "City": "Koppal",
    "Conc. name": "GMR",
    "Latitude": 15.819341,
    "Longitude": 76.174865
  },
  {
    "Plaza Code": 16002,
    "Plaza Name": "Shahapur",
    "Conc. Type": "Conc.",
    "Plaza Type": "TOLL",
    "Plaza Sub Type": "NATIONAL",
    "Sate": "Karnataka",
    "City": "Koppal",
    "Conc. name": "GMR",
    "Latitude": 15.357898,
    "Longitude": 76.312781
  },
  {
    "Plaza Code": 16003,
    "Plaza Name": "Hitnal",
    "Conc. Type": "Conc.",
    "Plaza Type": "TOLL",
    "Plaza Sub Type": "NATIONAL",
    "Sate": "Karnataka",
    "City": "Koppal",
    "Conc. name": "GMR",
    "Latitude": 15.323649,
    "Longitude": 76.303646
  },
  {
    "Plaza Code": 17001,
    "Plaza Name": "Karjeevanhally Toll\nPlaza",
    "Conc. Type": "Conc.",
    "Plaza Type": "TOLL",
    "Plaza Sub Type": "NATIONAL",
    "Sate": "Karnataka",
    "City": "Tumkur",
    "Conc. name": "IRB",
    "Latitude": 13.612918,
    "Longitude": 76.953866
  },
  {
    "Plaza Code": 17002,
    "Plaza Name": "Guilalu Toll Plaza",
    "Conc. Type": "Conc.",
    "Plaza Type": "TOLL",
    "Plaza Sub Type": "NATIONAL",
    "Sate": "Karnataka",
    "City": "Chitradurga",
    "Conc. name": "IRB",
    "Latitude": 14.053778,
    "Longitude": 76.560573
  },
  {
    "Plaza Code": 18001,
    "Plaza Name": "Vikkravandi Toll Plaza",
    "Conc. Type": "Conc.",
    "Plaza Type": "TOLL",
    "Plaza Sub Type": "NATIONAL",
    "Sate": "Tamil Nadu",
    "City": "Villupuram",
    "Conc. name": "Ulundurp\net\nExpressw\nay(IDFC)",
    "Latitude": 12.024441,
    "Longitude": 79.538059
  },
  {
    "Plaza Code": 19001,
    "Plaza Name": "SENGURICHI TOLL\nPLAZA",
    "Conc. Type": "Conc.",
    "Plaza Type": "TOLL",
    "Plaza Sub Type": "NATIONAL",
    "Sate": "Tamil Nadu",
    "City": "Villupuram",
    "Conc. name": "Trichy\nTollways\nPvt Ltd",
    "Latitude": 11.706434,
    "Longitude": 79.322335
  },
  {
    "Plaza Code": 19002,
    "Plaza Name": "THIRUMANDURAI\nTOLL PLAZA",
    "Conc. Type": "Conc.",
    "Plaza Type": "TOLL",
    "Plaza Sub Type": "NATIONAL",
    "Sate": "Tamil Nadu",
    "City": "Perambalur",
    "Conc. name": "Trichy\nTollways\nPvt Ltd",
    "Latitude": 11.396808,
    "Longitude": 78.99356
  },
  {
    "Plaza Code": 29001,
    "Plaza Name": "Laxamannath Plaza",
    "Conc. Type": "Conc.",
    "Plaza Type": "TOLL",
    "Plaza Sub Type": "NATIONAL",
    "Sate": "Karnataka",
    "City": "Bangalore\nRural",
    "Conc. name": "NHAI",
    "Latitude": 13.193545,
    "Longitude": 77.64981
  },
  {
    "Plaza Code": 32001,
    "Plaza Name": "Omalur Toll Plaza",
    "Conc. Type": "Conc.",
    "Plaza Type": "TOLL",
    "Plaza Sub Type": "NATIONAL",
    "Sate": "Tamil Nadu",
    "City": "Salem",
    "Conc. name": "IRB",
    "Latitude": 11.72034,
    "Longitude": 78.07338
  },
  {
    "Plaza Code": 35001,
    "Plaza Name": "ELECTRONIC CITY\nPhase 1",
    "Conc. Type": "Conc.",
    "Plaza Type": "TOLL",
    "Plaza Sub Type": "NATIONAL",
    "Sate": "Karnataka",
    "City": "Bangalore\nUrban",
    "Conc. name": "NAVAYUG\nA UDUPI\nTOLLWAY\nPVT LTD",
    "Latitude": 12.84615,
    "Longitude": 77.671765
  },
  {
    "Plaza Code": 35002,
    "Plaza Name": "ATTIBELLE",
    "Conc. Type": "Conc.",
    "Plaza Type": "TOLL",
    "Plaza Sub Type": "NATIONAL",
    "Sate": "Karnataka",
    "City": "Bangalore\nUrban",
    "Conc. name": "BETL",
    "Latitude": 12.776883,
    "Longitude": 77.777119
  },
  {
    "Plaza Code": 36001,
    "Plaza Name": "Samayapuram Toll\nPlaza",
    "Conc. Type": "Conc.",
    "Plaza Type": "TOLL",
    "Plaza Sub Type": "NATIONAL",
    "Sate": "Tamil Nadu",
    "City": "Tiruchirappalli",
    "Conc. name": "Indu\nNavayuga",
    "Latitude": 10.92937,
    "Longitude": 78.744056
  },
  {
    "Plaza Code": 42001,
    "Plaza Name": "Vijayamangalam Toll\nPlaza",
    "Conc. Type": "Conc.",
    "Plaza Type": "TOLL",
    "Plaza Sub Type": "NATIONAL",
    "Sate": "Tamil Nadu",
    "City": "Erode",
    "Conc. name": "IVRCL",
    "Latitude": 11.245714,
    "Longitude": 77.519702
  },
  {
    "Plaza Code": 43001,
    "Plaza Name": "Vaiguntham Toll\nPlaza",
    "Conc. Type": "Conc.",
    "Plaza Type": "TOLL",
    "Plaza Sub Type": "NATIONAL",
    "Sate": "Tamil Nadu",
    "City": "Salem",
    "Conc. name": "IVRCL",
    "Latitude": 11.513282,
    "Longitude": 77.923946
  },
  {
    "Plaza Code": 45001,
    "Plaza Name": "Guduru Toll Plaza",
    "Conc. Type": "Conc.",
    "Plaza Type": "TOLL",
    "Plaza Sub Type": "NATIONAL",
    "Sate": "Telangana",
    "City": "Nalgonda",
    "Conc. name": "Sadbhav",
    "Latitude": 17.485724,
    "Longitude": 78.8217
  },
  {
    "Plaza Code": 46001,
    "Plaza Name": "Bijapur Toll Plaza",
    "Conc. Type": "Conc.",
    "Plaza Type": "TOLL",
    "Plaza Sub Type": "NATIONAL",
    "Sate": "Karnataka",
    "City": "Bijapur",
    "Conc. name": "Sadbhav",
    "Latitude": 16.786741,
    "Longitude": 75.739648
  },
  {
    "Plaza Code": 46002,
    "Plaza Name": "Nagarhalla Toll Plaza",
    "Conc. Type": "Conc.",
    "Plaza Type": "TOLL",
    "Plaza Sub Type": "NATIONAL",
    "Sate": "Karnataka",
    "City": "Bagalkot",
    "Conc. name": "Sadbhav",
    "Latitude": 16.290371,
    "Longitude": 75.923507
  },
  {
    "Plaza Code": 55001,
    "Plaza Name": "Ponnambalapatti\nPlaza",
    "Conc. Type": "Conc.",
    "Plaza Type": "TOLL",
    "Plaza Sub Type": "NATIONAL",
    "Sate": "Tamil Nadu",
    "City": "Tiruchirappalli",
    "Conc. name": "Reliance",
    "Latitude": 10.536356,
    "Longitude": 78.257059
  },
  {
    "Plaza Code": 56001,
    "Plaza Name": "Kozhinjiipatti Plaza",
    "Conc. Type": "Conc.",
    "Plaza Type": "TOLL",
    "Plaza Sub Type": "NATIONAL",
    "Sate": "Tamil Nadu",
    "City": "Dindigul",
    "Conc. name": "Reliance",
    "Latitude": 10.194334,
    "Longitude": 77.909215
  },
  {
    "Plaza Code": 57001,
    "Plaza Name": "Rasampalayam Plaza",
    "Conc. Type": "Conc.",
    "Plaza Type": "TOLL",
    "Plaza Sub Type": "NATIONAL",
    "Sate": "Tamil Nadu",
    "City": "Namakkal",
    "Conc. name": "Reliance",
    "Latitude": 11.193895,
    "Longitude": 78.103219
  },
  {
    "Plaza Code": 58002,
    "Plaza Name": "Nathakkarai Plaza",
    "Conc. Type": "Conc.",
    "Plaza Type": "TOLL",
    "Plaza Sub Type": "NATIONAL",
    "Sate": "Tamil Nadu",
    "City": "Salem",
    "Conc. name": "Reliance",
    "Latitude": 11.592809,
    "Longitude": 78.780812
  },
  {
    "Plaza Code": 58003,
    "Plaza Name": "Veeracholapuram\nPlaza",
    "Conc. Type": "Conc.",
    "Plaza Type": "TOLL",
    "Plaza Sub Type": "NATIONAL",
    "Sate": "Tamil Nadu",
    "City": "Villupuram",
    "Conc. name": "Reliance",
    "Latitude": 11.736464,
    "Longitude": 79.010409
  },
  {
    "Plaza Code": 59001,
    "Plaza Name": "Thiruparaithurai\nPlaza",
    "Conc. Type": "Conc.",
    "Plaza Type": "TOLL",
    "Plaza Sub Type": "NATIONAL",
    "Sate": "Tamil Nadu",
    "City": "Tiruchirappalli",
    "Conc. name": "Reliance",
    "Latitude": 10.885791,
    "Longitude": 78.557668
  },
  {
    "Plaza Code": 59002,
    "Plaza Name": "Manavasi Plaza",
    "Conc. Type": "Conc.",
    "Plaza Type": "TOLL",
    "Plaza Sub Type": "NATIONAL",
    "Sate": "Tamil Nadu",
    "City": "Karur",
    "Conc. name": "Reliance",
    "Latitude": 10.931722,
    "Longitude": 78.218401
  },
  {
    "Plaza Code": 60001,
    "Plaza Name": "Krishnagiri Plaza",
    "Conc. Type": "Conc.",
    "Plaza Type": "TOLL",
    "Plaza Sub Type": "NATIONAL",
    "Sate": "Tamil Nadu",
    "City": "Krishnagiri",
    "Conc. name": "Reliance",
    "Latitude": 12.544583,
    "Longitude": 78.201132
  },
  {
    "Plaza Code": 78001,
    "Plaza Name": "Indalwai",
    "Conc. Type": "Conc.",
    "Plaza Type": "TOLL",
    "Plaza Sub Type": "NATIONAL",
    "Sate": "Telangana",
    "City": "Nizamabad",
    "Conc. name": "Navayuga",
    "Latitude": 18.538284,
    "Longitude": 78.239718
  },
  {
    "Plaza Code": 79001,
    "Plaza Name": "Sakapur Toll plaza",
    "Conc. Type": "Conc.",
    "Plaza Type": "TOLL",
    "Plaza Sub Type": "NATIONAL",
    "Sate": "Telangana",
    "City": "Mahabubnaga\nr",
    "Conc. name": "L&T",
    "Latitude": 16.5356759,
    "Longitude": 77.9444736
  },
  {
    "Plaza Code": 111001,
    "Plaza Name": "Hirebgewadi toll\nplaza",
    "Conc. Type": "Conc.",
    "Plaza Type": "TOLL",
    "Plaza Sub Type": "NATIONAL",
    "Sate": "Karnataka",
    "City": "Belagavi",
    "Conc. name": "Ashoka\nBuildcon",
    "Latitude": 15.76311,
    "Longitude": 74.64785
  },
  {
    "Plaza Code": 115001,
    "Plaza Name": "Kulumapalya toll\nplaza",
    "Conc. Type": "Conc.",
    "Plaza Type": "TOLL",
    "Plaza Sub Type": "NATIONAL",
    "Sate": "Karnataka",
    "City": "Bangalore\nRural",
    "Conc. name": "Jass\nTollways",
    "Latitude": 13.114638,
    "Longitude": 77.37463
  },
  {
    "Plaza Code": 115002,
    "Plaza Name": "Chokkenahalli toll\nplaza",
    "Conc. Type": "Conc.",
    "Plaza Type": "TOLL",
    "Plaza Sub Type": "NATIONAL",
    "Sate": "Karnataka",
    "City": "Tumkur",
    "Conc. name": "Jass\nTollways",
    "Latitude": 13.302065,
    "Longitude": 77.161956
  },
  {
    "Plaza Code": 116001,
    "Plaza Name": "Banglaore-\nNelamangala Plaza",
    "Conc. Type": "Conc.",
    "Plaza Type": "TOLL",
    "Plaza Sub Type": "NATIONAL",
    "Sate": "Karnataka",
    "City": "Bangalore\nRural",
    "Conc. name": "Navayuga",
    "Latitude": 13.090678,
    "Longitude": 77.399788
  },
  {
    "Plaza Code": 116003,
    "Plaza Name": "Devanahalli Toll Plaza",
    "Conc. Type": "Conc.",
    "Plaza Type": "TOLL",
    "Plaza Sub Type": "NATIONAL",
    "Sate": "Karnataka",
    "City": "Bangalore\nRural",
    "Conc. name": "Navayuga",
    "Latitude": 13.1935464,
    "Longitude": 77.6475256
  },
  {
    "Plaza Code": 118001,
    "Plaza Name": "Nelamangala Toll\nPlaza",
    "Conc. Type": "Conc.",
    "Plaza Type": "TOLL",
    "Plaza Sub Type": "NATIONAL",
    "Sate": "Karnataka",
    "City": "Bangalore\nRural",
    "Conc. name": "LANCO\nDEVANHA\nLI\nTOLLWAY\nLTD",
    "Latitude": 13.0924871,
    "Longitude": 77.3944374
  },
  {
    "Plaza Code": 119001,
    "Plaza Name": "Hoskote Toll Plaza",
    "Conc. Type": "Conc.",
    "Plaza Type": "TOLL",
    "Plaza Sub Type": "NATIONAL",
    "Sate": "Karnataka",
    "City": "Bangalore\nRural",
    "Conc. name": "LANCO\nHOSKOTE\nTOLLWAY\nLTD",
    "Latitude": 13.059436,
    "Longitude": 77.770734
  },
  {
    "Plaza Code": 119002,
    "Plaza Name": "Mulbagal Toll Plaza",
    "Conc. Type": "Conc.",
    "Plaza Type": "TOLL",
    "Plaza Sub Type": "NATIONAL",
    "Sate": "Karnataka",
    "City": "Kolar",
    "Conc. name": "LANCO\nHOSKOTE\nTOLLWAY\nLTD",
    "Latitude": 13.148469,
    "Longitude": 78.290548
  },
  {
    "Plaza Code": 120001,
    "Plaza Name": "Shantigrama Toll\nPlaza",
    "Conc. Type": "Conc.",
    "Plaza Type": "TOLL",
    "Plaza Sub Type": "NATIONAL",
    "Sate": "Karnataka",
    "City": "Hassan",
    "Conc. name": "L&T",
    "Latitude": 12.982709,
    "Longitude": 76.228913
  },
  {
    "Plaza Code": 120002,
    "Plaza Name": "Kadabhalli (Kirasave)\nToll Pl",
    "Conc. Type": "Conc.",
    "Plaza Type": "TOLL",
    "Plaza Sub Type": "NATIONAL",
    "Sate": "Karnataka",
    "City": "Mandya",
    "Conc. name": "L&T",
    "Latitude": 12.958304,
    "Longitude": 76.623563
  },
  {
    "Plaza Code": 123001,
    "Plaza Name": "Paliyekkara Toll plaza",
    "Conc. Type": "Conc.",
    "Plaza Type": "TOLL",
    "Plaza Sub Type": "NATIONAL",
    "Sate": "Kerala",
    "City": "Thrissur",
    "Conc. name": "Guruvayo\nor",
    "Latitude": 10.442916,
    "Longitude": 76.260181
  },
  {
    "Plaza Code": 124001,
    "Plaza Name": "Kumbalam Toll Plaza",
    "Conc. Type": "Conc.",
    "Plaza Type": "TOLL",
    "Plaza Sub Type": "NATIONAL",
    "Sate": "Kerala",
    "City": "Ernakulam",
    "Conc. name": "Kochi\nAror\nTollways",
    "Latitude": 9.895245,
    "Longitude": 76.313541
  },
  {
    "Plaza Code": 167001,
    "Plaza Name": "Vaniyambadi Toll\nPlaza",
    "Conc. Type": "Conc.",
    "Plaza Type": "TOLL",
    "Plaza Sub Type": "NATIONAL",
    "Sate": "Tamil Nadu",
    "City": "Vellore",
    "Conc. name": "L&T",
    "Latitude": 12.648554,
    "Longitude": 78.5833
  },
  {
    "Plaza Code": 167002,
    "Plaza Name": "Pallikonda Toll Plaza",
    "Conc. Type": "Conc.",
    "Plaza Type": "TOLL",
    "Plaza Sub Type": "NATIONAL",
    "Sate": "Tamil Nadu",
    "City": "Vellore",
    "Conc. name": "L&T",
    "Latitude": 12.905829,
    "Longitude": 78.951686
  },
  {
    "Plaza Code": 169001,
    "Plaza Name": "L&T Krishnagiri\nThopur Toll P",
    "Conc. Type": "Conc.",
    "Plaza Type": "TOLL",
    "Plaza Sub Type": "NATIONAL",
    "Sate": "Tamil Nadu",
    "City": "Dharmapuri",
    "Conc. name": "L&T",
    "Latitude": 12.00638,
    "Longitude": 78.08008
  },
  {
    "Plaza Code": 170001,
    "Plaza Name": "Velanchettiyur",
    "Conc. Type": "Conc.",
    "Plaza Type": "TOLL",
    "Plaza Sub Type": "NATIONAL",
    "Sate": "Tamil Nadu",
    "City": "Dindigul",
    "Conc. name": "Madhuco\nn Infra",
    "Latitude": 10.6990089,
    "Longitude": 77.93067
  },
  {
    "Plaza Code": 176001,
    "Plaza Name": "Valvanthankottai",
    "Conc. Type": "Conc.",
    "Plaza Type": "TOLL",
    "Plaza Sub Type": "NATIONAL",
    "Sate": "Tamil Nadu",
    "City": "Tiruchirappalli",
    "Conc. name": "Madhuco\nn Infra",
    "Latitude": 10.744371,
    "Longitude": 78.834044
  },
  {
    "Plaza Code": 176002,
    "Plaza Name": "Elliyarpathy",
    "Conc. Type": "Conc.",
    "Plaza Type": "TOLL",
    "Plaza Sub Type": "NATIONAL",
    "Sate": "Tamil Nadu",
    "City": "Virudhunagar",
    "Conc. name": "Madhuco\nn Infra",
    "Latitude": 9.78299,
    "Longitude": 78.094492
  },
  {
    "Plaza Code": 176003,
    "Plaza Name": "Pudurpandiyapuram",
    "Conc. Type": "Conc.",
    "Plaza Type": "TOLL",
    "Plaza Sub Type": "NATIONAL",
    "Sate": "Tamil Nadu",
    "City": "Thoothukudi",
    "Conc. name": "Madhuco\nn Infra",
    "Latitude": 8.862935,
    "Longitude": 78.117106
  },
  {
    "Plaza Code": 177001,
    "Plaza Name": "Pondicherry\nTindivanam Toll P",
    "Conc. Type": "Conc.",
    "Plaza Type": "TOLL",
    "Plaza Sub Type": "NATIONAL",
    "Sate": "Tamil Nadu",
    "City": "Villupuram",
    "Conc. name": "Pondicher\nry\nTollways",
    "Latitude": 11.983278,
    "Longitude": 79.78836
  },
  {
    "Plaza Code": 230001,
    "Plaza Name": "IVRCL Chengapally\nTollways Li",
    "Conc. Type": "Conc.",
    "Plaza Type": "TOLL",
    "Plaza Sub Type": "NATIONAL",
    "Sate": "Tamil Nadu",
    "City": "Tiruppur",
    "Conc. name": "IVRCL",
    "Latitude": 11.012852,
    "Longitude": 77.073167
  },
  {
    "Plaza Code": 239600,
    "Plaza Name": "Nangli Toll Plaza",
    "Conc. Type": "Conc.",
    "Plaza Type": "TOLL",
    "Plaza Sub Type": "NATIONAL",
    "Sate": "Karnataka",
    "City": "Kolar",
    "Conc. name": "JSRMTPL",
    "Latitude": 13.194547,
    "Longitude": 78.545287
  },
  {
    "Plaza Code": 239700,
    "Plaza Name": "PamPamPallam Toll\nPlaza",
    "Conc. Type": "Conc.",
    "Plaza Type": "TOLL",
    "Plaza Sub Type": "NATIONAL",
    "Sate": "Kerala",
    "City": "Palakkad",
    "Conc. name": "KNR\nWalayar\nTollways\nPvt Ltd",
    "Latitude": 10.8131538,
    "Longitude": 76.7957998
  },
  {
    "Plaza Code": 257001,
    "Plaza Name": "Sasthan Toll Plaza",
    "Conc. Type": "Conc.",
    "Plaza Type": "TOLL",
    "Plaza Sub Type": "NATIONAL",
    "Sate": "Karnataka",
    "City": "Sasthan",
    "Conc. name": "Navayuga",
    "Latitude": 13.476043,
    "Longitude": 74.7127896
  },
  {
    "Plaza Code": 257002,
    "Plaza Name": "HEJAMADI TOLL\nPLAZA",
    "Conc. Type": "Conc.",
    "Plaza Type": "TOLL",
    "Plaza Sub Type": "NATIONAL",
    "Sate": "Karnataka",
    "City": "Hejamadi",
    "Conc. name": "NAVAYUG\nA UDUPI\nTOLLWAY\nPVT LTD",
    "Latitude": 13.1075003,
    "Longitude": 74.7844545763
  },
  {
    "Plaza Code": 257003,
    "Plaza Name": "TALAPADY TOLL\nPLAZA",
    "Conc. Type": "Conc.",
    "Plaza Type": "TOLL",
    "Plaza Sub Type": "NATIONAL",
    "Sate": "Karnataka",
    "City": "Talapady",
    "Conc. name": "NAVAYUG\nA UDUPI\nTOLLWAY\nPVT LTD",
    "Latitude": 12.7590772,
    "Longitude": 74.8743029
  },
  {
    "Plaza Code": 340057,
    "Plaza Name": "Gananguru Toll Plaza",
    "Conc. Type": "PF",
    "Plaza Type": "TOLL",
    "Plaza Sub Type": "NATIONAL",
    "Sate": "Karnataka",
    "City": "Mandiya",
    "Conc. name": "NHAI",
    "Latitude": 12.472697,
    "Longitude": 76.760373
  },
  {
    "Plaza Code": 350004,
    "Plaza Name": "Chinthapally Toll\nPlaza",
    "Conc. Type": "PF",
    "Plaza Type": "TOLL",
    "Plaza Sub Type": "NATIONAL",
    "Sate": "Telangana",
    "City": "Chinthapally",
    "Conc. name": "NHAI",
    "Latitude": 17.471528,
    "Longitude": 79.980556
  },
  {
    "Plaza Code": 350005,
    "Plaza Name": "Kadthal Toll Plaza",
    "Conc. Type": "PF",
    "Plaza Type": "TOLL",
    "Plaza Sub Type": "NATIONAL",
    "Sate": "Telangana",
    "City": "Kadthal",
    "Conc. name": "NHAI",
    "Latitude": 16.970404,
    "Longitude": 78.50755
  },
  {
    "Plaza Code": 350006,
    "Plaza Name": "Pullur Toll Plaza",
    "Conc. Type": "PF",
    "Plaza Type": "TOLL",
    "Plaza Sub Type": "NATIONAL",
    "Sate": "Telangana",
    "City": "Mahabubnaga\nr",
    "Conc. name": "NHAI",
    "Latitude": 15.887742,
    "Longitude": 78.016978
  },
  {
    "Plaza Code": 350007,
    "Plaza Name": "Rolmamda Toll Plaza",
    "Conc. Type": "PF",
    "Plaza Type": "TOLL",
    "Plaza Sub Type": "NATIONAL",
    "Sate": "Telangana",
    "City": "Adilabad",
    "Conc. name": "NHAI",
    "Latitude": 19.28019,
    "Longitude": 78.409222
  },
  {
    "Plaza Code": 350008,
    "Plaza Name": "Gamjal Toll Plaza",
    "Conc. Type": "PF",
    "Plaza Type": "TOLL",
    "Plaza Sub Type": "NATIONAL",
    "Sate": "Telangana",
    "City": "Adilabad",
    "Conc. name": "NHAI",
    "Latitude": 19.026592,
    "Longitude": 78.362705
  },
  {
    "Plaza Code": 350026,
    "Plaza Name": "Konetipuram",
    "Conc. Type": "PF",
    "Plaza Type": "TOLL",
    "Plaza Sub Type": "NATIONAL",
    "Sate": "Telangana",
    "City": "Konetipuram",
    "Conc. name": "NHAI",
    "Latitude": 16.6120211,
    "Longitude": 78.6758205
  },
  {
    "Plaza Code": 350027,
    "Plaza Name": "Manoharabad",
    "Conc. Type": "PF",
    "Plaza Type": "TOLL",
    "Plaza Sub Type": "NATIONAL",
    "Sate": "Telangana",
    "City": "Medak",
    "Conc. name": "NHAI",
    "Latitude": 17.801103,
    "Longitude": 78.471683
  },
  {
    "Plaza Code": 350028,
    "Plaza Name": "Pippalwada",
    "Conc. Type": "PF",
    "Plaza Type": "TOLL",
    "Plaza Sub Type": "NATIONAL",
    "Sate": "Telangana",
    "City": "Adilabad",
    "Conc. name": "NHAI",
    "Latitude": 19.781093,
    "Longitude": 78.565772
  },
  {
    "Plaza Code": 350029,
    "Plaza Name": "Bhiknoor Toll Plaza",
    "Conc. Type": "PF",
    "Plaza Type": "TOLL",
    "Plaza Sub Type": "NATIONAL",
    "Sate": "Telangana",
    "City": "Nizamabad",
    "Conc. name": "NHAI",
    "Latitude": 18.20539,
    "Longitude": 78.398299
  },
  {
    "Plaza Code": 350030,
    "Plaza Name": "Gowraram Toll Plaza",
    "Conc. Type": "PF",
    "Plaza Type": "TOLL",
    "Plaza Sub Type": "NATIONAL",
    "Sate": "Telangana",
    "City": "Gowraran\nvillage",
    "Conc. name": "NHAI",
    "Latitude": 17.268021,
    "Longitude": 80.679776
  },
  {
    "Plaza Code": 350031,
    "Plaza Name": "Komalla Fee Plaza",
    "Conc. Type": "PF",
    "Plaza Type": "TOLL",
    "Plaza Sub Type": "NATIONAL",
    "Sate": "Telangana",
    "City": "Komalla (V)",
    "Conc. name": "NHAI",
    "Latitude": 17.77737111,
    "Longitude": 79.28361111
  },
  {
    "Plaza Code": 350033,
    "Plaza Name": "Muthojipet",
    "Conc. Type": "PF",
    "Plaza Type": "TOLL",
    "Plaza Sub Type": "NATIONAL",
    "Sate": "Telangana",
    "City": "Vijayawada",
    "Conc. name": "NHAI",
    "Latitude": 17.9740755,
    "Longitude": 79.9144659
  },
  {
    "Plaza Code": 350034,
    "Plaza Name": "Dilawarpur fee plaza",
    "Conc. Type": "PF.",
    "Plaza Type": "TOLL",
    "Plaza Sub Type": "NATIONAL",
    "Sate": "Telangana",
    "City": "Bodhan",
    "Conc. name": "NHAI",
    "Latitude": 19.0989609,
    "Longitude": 78.2133902
  },
  {
    "Plaza Code": 350035,
    "Plaza Name": "Singarajupally Toll\nPlaza",
    "Conc. Type": "PF",
    "Plaza Type": "TOLL",
    "Plaza Sub Type": "NATIONAL",
    "Sate": "Telangana",
    "City": "Suryapet",
    "Conc. name": "NHAI",
    "Latitude": 17.589631,
    "Longitude": 79.276944
  },
  {
    "Plaza Code": 350036,
    "Plaza Name": "Yerkaram Toll Plaza",
    "Conc. Type": "PF",
    "Plaza Type": "TOLL",
    "Plaza Sub Type": "NATIONAL",
    "Sate": "Telangana",
    "City": "Suryapet",
    "Conc. name": "NHAI",
    "Latitude": 17.247402,
    "Longitude": 79.580502
  },
  {
    "Plaza Code": 350040,
    "Plaza Name": "Singarenipalli Toll\nPlaza",
    "Conc. Type": "PF",
    "Plaza Type": "TOLL",
    "Plaza Sub Type": "NATIONAL",
    "Sate": "Telangana",
    "City": "Suryapet",
    "Conc. name": "NHAI",
    "Latitude": 17.192,
    "Longitude": 79.871
  },
  {
    "Plaza Code": 350041,
    "Plaza Name": "Mandamarri Toll\nPlaza",
    "Conc. Type": "PF",
    "Plaza Type": "TOLL",
    "Plaza Sub Type": "NATIONAL",
    "Sate": "Telangana",
    "City": "Mandamarri",
    "Conc. name": "NHAI",
    "Latitude": 19.011289,
    "Longitude": 79.478191
  },
  {
    "Plaza Code": 350042,
    "Plaza Name": "Taddanpally Toll\nPlaza",
    "Conc. Type": "PF",
    "Plaza Type": "TOLL",
    "Plaza Sub Type": "NATIONAL",
    "Sate": "Telangana",
    "City": "Taddanpally",
    "Conc. name": "NHAI",
    "Latitude": 17.695444,
    "Longitude": 78.095667
  },
  {
    "Plaza Code": 350044,
    "Plaza Name": "Pudur Toll Plaza",
    "Conc. Type": "PF",
    "Plaza Type": "TOLL",
    "Plaza Sub Type": "NATIONAL",
    "Sate": "Tamil Nadu",
    "City": "Madurai",
    "Conc. name": "NHAI",
    "Latitude": 10.11086,
    "Longitude": 78.17934
  },
  {
    "Plaza Code": 350100,
    "Plaza Name": "Kamkole",
    "Conc. Type": "Conc.",
    "Plaza Type": "TOLL",
    "Plaza Sub Type": "NATIONAL",
    "Sate": "Telangana",
    "City": "Bidar",
    "Conc. name": "M/s\nDeccan\nTollways\nLtd",
    "Latitude": 17.6457252,
    "Longitude": 77.8198176
  },
  {
    "Plaza Code": 350101,
    "Plaza Name": "Munnanur Toll Plaza",
    "Conc. Type": "PF",
    "Plaza Type": "TOLL",
    "Plaza Sub Type": "NATIONAL",
    "Sate": "Telangana",
    "City": "Munnanur",
    "Conc. name": "NHAI",
    "Latitude": 16.7455098506,
    "Longitude": 418178.2853169779
  },
  {
    "Plaza Code": 350102,
    "Plaza Name": "Chitlapalli Toll Plaza",
    "Conc. Type": "PF.",
    "Plaza Type": "TOLL",
    "Plaza Sub Type": "NATIONAL",
    "Sate": "Telangana",
    "City": "Chitlapalli",
    "Conc. name": "NHAI",
    "Latitude": 17.0811,
    "Longitude": 77.581
  },
  {
    "Plaza Code": 350103,
    "Plaza Name": "Gummadidala Toll\nPlaza",
    "Conc. Type": "PF",
    "Plaza Type": "TOLL",
    "Plaza Sub Type": "NATIONAL",
    "Sate": "Telangana",
    "City": "Gummadidala",
    "Conc. name": "NHAI",
    "Latitude": 29.9105,
    "Longitude": 76.50713
  },
  {
    "Plaza Code": 350104,
    "Plaza Name": "Dharmaram Toll\nPlaza",
    "Conc. Type": "PF.",
    "Plaza Type": "TOLL",
    "Plaza Sub Type": "NATIONAL",
    "Sate": "Telangana",
    "City": "Pitlam",
    "Conc. name": "NHAI",
    "Latitude": 18.2658,
    "Longitude": 77.7871
  },
  {
    "Plaza Code": 352058,
    "Plaza Name": "Jawahar Nagar Toll\nPlaza",
    "Conc. Type": "PF.",
    "Plaza Type": "TOLL",
    "Plaza Sub Type": "NATIONAL",
    "Sate": "Telangana",
    "City": "Mulugu",
    "Conc. name": "NHAI",
    "Latitude": 18.212011,
    "Longitude": 80.0284
  },
  {
    "Plaza Code": 356006,
    "Plaza Name": "Belekeri",
    "Conc. Type": "Conc.",
    "Plaza Type": "TOLL",
    "Plaza Sub Type": "NATIONAL",
    "Sate": "Karnataka",
    "City": "Hattikeri",
    "Conc. name": "IRB\nWestcoas\nt Tollway",
    "Latitude": 14.7104272,
    "Longitude": 74.2935113
  },
  {
    "Plaza Code": 356007,
    "Plaza Name": "Holgegadde",
    "Conc. Type": "Conc.",
    "Plaza Type": "TOLL",
    "Plaza Sub Type": "NATIONAL",
    "Sate": "Karnataka",
    "City": "Dhareshwar",
    "Conc. name": "IRB\nWestcoas\nt Tollway",
    "Latitude": 14.3594475,
    "Longitude": 74.4184843
  },
  {
    "Plaza Code": 356008,
    "Plaza Name": "Shirur",
    "Conc. Type": "Conc.",
    "Plaza Type": "TOLL",
    "Plaza Sub Type": "NATIONAL",
    "Sate": "Karnataka",
    "City": "Shiroor",
    "Conc. name": "IRB\nWestcoas\nt Tollway",
    "Latitude": 13.9333649,
    "Longitude": 74.5965095
  },
  {
    "Plaza Code": 356009,
    "Plaza Name": "Gabbur",
    "Conc. Type": "Conc.",
    "Plaza Type": "TOLL",
    "Plaza Sub Type": "NATIONAL",
    "Sate": "Karnataka",
    "City": "Hubli",
    "Conc. name": "Nandi\nHighway\nDevelope\nrs",
    "Latitude": 15.3186929,
    "Longitude": 75.1398824
  },
  {
    "Plaza Code": 356010,
    "Plaza Name": "Karwar",
    "Conc. Type": "Conc.",
    "Plaza Type": "TOLL",
    "Plaza Sub Type": "NATIONAL",
    "Sate": "Karnataka",
    "City": "Hubli",
    "Conc. name": "Nandi\nHighway\nDevelope\nrs",
    "Latitude": 15.4461808,
    "Longitude": 75.0125785
  },
  {
    "Plaza Code": 356011,
    "Plaza Name": "Tarihal",
    "Conc. Type": "Conc.",
    "Plaza Type": "TOLL",
    "Plaza Sub Type": "NATIONAL",
    "Sate": "Karnataka",
    "City": "Hubli",
    "Conc. name": "Nandi\nHighway\nDevelope\nrs",
    "Latitude": 15.359531,
    "Longitude": 75.051265
  },
  {
    "Plaza Code": 356012,
    "Plaza Name": "Kalghatgi",
    "Conc. Type": "Conc.",
    "Plaza Type": "TOLL",
    "Plaza Sub Type": "NATIONAL",
    "Sate": "Karnataka",
    "City": "Dharwad",
    "Conc. name": "Nandi\nHighway\nDevelope\nrs",
    "Latitude": 15.396148,
    "Longitude": 75.004123
  },
  {
    "Plaza Code": 356013,
    "Plaza Name": "Goa",
    "Conc. Type": "Conc.",
    "Plaza Type": "TOLL",
    "Plaza Sub Type": "NATIONAL",
    "Sate": "Karnataka",
    "City": "Dharwad",
    "Conc. name": "Nandi\nHighway\nDevelope\nrs",
    "Latitude": 15.460555,
    "Longitude": 74.967151
  },
  {
    "Plaza Code": 356014,
    "Plaza Name": "Narendra",
    "Conc. Type": "Conc.",
    "Plaza Type": "TOLL",
    "Plaza Sub Type": "NATIONAL",
    "Sate": "Karnataka",
    "City": "Dharwad",
    "Conc. name": "Nandi\nHighway\nDevelope\nrs",
    "Latitude": 15.488805,
    "Longitude": 74.970109
  },
  {
    "Plaza Code": 356016,
    "Plaza Name": "Bankapur",
    "Conc. Type": "PF",
    "Plaza Type": "TOLL",
    "Plaza Sub Type": "NATIONAL",
    "Sate": "Karnataka",
    "City": "Haveri",
    "Conc. name": "NHAI",
    "Latitude": 14.90999,
    "Longitude": 75.2798
  },
  {
    "Plaza Code": 356018,
    "Plaza Name": "Kognoli Toll Plaza",
    "Conc. Type": "PF",
    "Plaza Type": "TOLL",
    "Plaza Sub Type": "NATIONAL",
    "Sate": "Karnataka",
    "City": "Belagavi",
    "Conc. name": "NHAI",
    "Latitude": 16.5422,
    "Longitude": 74.31825
  },
  {
    "Plaza Code": 356019,
    "Plaza Name": "Chalageri Toll Plaza",
    "Conc. Type": "PF",
    "Plaza Type": "TOLL",
    "Plaza Sub Type": "NATIONAL",
    "Sate": "Karnataka",
    "City": "Haveri",
    "Conc. name": "NHAI",
    "Latitude": 14.556782,
    "Longitude": 75.728072
  },
  {
    "Plaza Code": 356020,
    "Plaza Name": "Hebbalu Toll Plaza",
    "Conc. Type": "PF",
    "Plaza Type": "TOLL",
    "Plaza Sub Type": "NATIONAL",
    "Sate": "Karnataka",
    "City": "Davanagere",
    "Conc. name": "NHAI",
    "Latitude": 14.375564,
    "Longitude": 76.106875
  },
  {
    "Plaza Code": 356021,
    "Plaza Name": "Hattargi Toll Plaza",
    "Conc. Type": "PF",
    "Plaza Type": "TOLL",
    "Plaza Sub Type": "NATIONAL",
    "Sate": "Karnataka",
    "City": "Belagavi",
    "Conc. name": "NHAI",
    "Latitude": 16.1433,
    "Longitude": 74.51696
  },
  {
    "Plaza Code": 356023,
    "Plaza Name": "Brahamarakotlu Toll\nPlaza",
    "Conc. Type": "PF",
    "Plaza Type": "TOLL",
    "Plaza Sub Type": "NATIONAL",
    "Sate": "Karnataka",
    "City": "Dakshina\nKannada",
    "Conc. name": "NHAI",
    "Latitude": 12.8751,
    "Longitude": 75.0039
  },
  {
    "Plaza Code": 356024,
    "Plaza Name": "Yeddore Toll Plaza",
    "Conc. Type": "PF",
    "Plaza Type": "TOLL",
    "Plaza Sub Type": "NATIONAL",
    "Sate": "Karnataka",
    "City": "Mysore",
    "Conc. name": "NHAI",
    "Latitude": 12.247019,
    "Longitude": 76.883537
  },
  {
    "Plaza Code": 356025,
    "Plaza Name": "K N Huindy TOLL\nPLAZA",
    "Conc. Type": "PF",
    "Plaza Type": "TOLL",
    "Plaza Sub Type": "NATIONAL",
    "Sate": "Karnataka",
    "City": "Ramanagara",
    "Conc. name": "NHAI",
    "Latitude": 12.9194122,
    "Longitude": 77.4686378
  },
  {
    "Plaza Code": 356026,
    "Plaza Name": "Kannole TOLL PLAZA",
    "Conc. Type": "PF",
    "Plaza Type": "TOLL",
    "Plaza Sub Type": "NATIONAL",
    "Sate": "Karnataka",
    "City": "Gulbarga",
    "Conc. name": "NHAI",
    "Latitude": 17.3970044,
    "Longitude": 76.7064433
  },
  {
    "Plaza Code": 356027,
    "Plaza Name": "Harwal TOLL PLAZA",
    "Conc. Type": "PF",
    "Plaza Type": "TOLL",
    "Plaza Sub Type": "NATIONAL",
    "Sate": "Karnataka",
    "City": "Gulbarga",
    "Conc. name": "NHAI",
    "Latitude": 17.021227,
    "Longitude": 76.6828832
  },
  {
    "Plaza Code": 356028,
    "Plaza Name": "Kannegala TOLL\nPLAZA",
    "Conc. Type": "PF",
    "Plaza Type": "TOLL",
    "Plaza Sub Type": "NATIONAL",
    "Sate": "Karnataka",
    "City": "Malavalli",
    "Conc. name": "NHAI",
    "Latitude": 11.981411,
    "Longitude": 76.996146
  },
  {
    "Plaza Code": 356029,
    "Plaza Name": "Hirehalli Toll plaza",
    "Conc. Type": "PF",
    "Plaza Type": "TOLL",
    "Plaza Sub Type": "NATIONAL",
    "Sate": "Karnataka",
    "City": "Hirehalli",
    "Conc. name": "NHAI",
    "Latitude": 14.524962,
    "Longitude": 76.6644745
  },
  {
    "Plaza Code": 356030,
    "Plaza Name": "Tidagundi",
    "Conc. Type": "BOT.",
    "Plaza Type": "TOLL",
    "Plaza Sub Type": "NATIONAL",
    "Sate": "Karnataka",
    "City": "Vijayapura",
    "Conc. name": "Vijayapur\na Toll\npass",
    "Latitude": 17.00835,
    "Longitude": 75.75887
  },
  {
    "Plaza Code": 356100,
    "Plaza Name": "Mangalgi",
    "Conc. Type": "Conc.",
    "Plaza Type": "TOLL",
    "Plaza Sub Type": "NATIONAL",
    "Sate": "Karnataka",
    "City": "Bidar",
    "Conc. name": "M/s\nDeccan\nTollways\nLtd",
    "Latitude": 17.7454925,
    "Longitude": 77.3171313
  },
  {
    "Plaza Code": 356103,
    "Plaza Name": "Thimmalapura",
    "Conc. Type": "Conc.",
    "Plaza Type": "TOLL",
    "Plaza Sub Type": "NATIONAL",
    "Sate": "Karnataka",
    "City": "Bellary",
    "Conc. name": "Hampi\nExpressw\nays PVT.\nLTD.",
    "Latitude": 15.05737,
    "Longitude": 76.3569
  },
  {
    "Plaza Code": 356104,
    "Plaza Name": "Kananakatte",
    "Conc. Type": "Conc.",
    "Plaza Type": "TOLL",
    "Plaza Sub Type": "NATIONAL",
    "Sate": "Karnataka",
    "City": "Davangere",
    "Conc. name": "Hampi\nExpressw\nays PVT.\nLTD.",
    "Latitude": 14.5381,
    "Longitude": 76.4269
  },
  {
    "Plaza Code": 356106,
    "Plaza Name": "Nalavadi",
    "Conc. Type": "PF",
    "Plaza Type": "TOLL",
    "Plaza Sub Type": "NATIONAL",
    "Sate": "Karnataka",
    "City": "Nalavadi",
    "Conc. name": "SRI SAI\nENTERPRI\nSES",
    "Latitude": 15.369872021,
    "Longitude": 2286875.357446335
  },
  {
    "Plaza Code": 356107,
    "Plaza Name": "Halligudi Fee Plaza",
    "Conc. Type": "PF",
    "Plaza Type": "TOLL",
    "Plaza Sub Type": "NATIONAL",
    "Sate": "Karnataka",
    "City": "Halligudi",
    "Conc. name": "BSCPL\nInfrastruc\nture Ltd",
    "Latitude": 15.3909,
    "Longitude": 75.8551
  },
  {
    "Plaza Code": 356108,
    "Plaza Name": "Jajirakallu Toll Plaza",
    "Conc. Type": "Conc.",
    "Plaza Type": "TOLL",
    "Plaza Sub Type": "NATIONAL",
    "Sate": "Karnataka",
    "City": "Jajirakallu",
    "Conc. name": "Sri Sai\nEnterpris\nes",
    "Latitude": 14.98163,
    "Longitude": 76.834694
  },
  {
    "Plaza Code": 356110,
    "Plaza Name": "Sheshagirihalli Toll\nPlaza",
    "Conc. Type": "PF",
    "Plaza Type": "TOLL",
    "Plaza Sub Type": "NATIONAL",
    "Sate": "Karnataka",
    "City": "Ramanagar",
    "Conc. name": "DBL\nBangalore\nNidagatta\nHwy",
    "Latitude": 12.84035,
    "Longitude": 77.41846
  },
  {
    "Plaza Code": 356111,
    "Plaza Name": "Kaniminike Toll Plaza",
    "Conc. Type": "PF",
    "Plaza Type": "TOLL",
    "Plaza Sub Type": "NATIONAL",
    "Sate": "Karnataka",
    "City": "Bengaluru",
    "Conc. name": "DBL\nBangalore\nNidagatta\nHwy",
    "Latitude": 12.8596,
    "Longitude": 77.43111
  },
  {
    "Plaza Code": 356112,
    "Plaza Name": "Ganebail Toll Plaza",
    "Conc. Type": "PF",
    "Plaza Type": "TOLL",
    "Plaza Sub Type": "NATIONAL",
    "Sate": "Karnataka",
    "City": "Belgaon",
    "Conc. name": "Coral\nAssociate",
    "Latitude": 15.692835,
    "Longitude": 74.503531
  },
  {
    "Plaza Code": 360020,
    "Plaza Name": "Pollachi Cochin Toll\nPlaza",
    "Conc. Type": "Conc.",
    "Plaza Type": "TOLL",
    "Plaza Sub Type": "NATIONAL",
    "Sate": "Tamil Nadu",
    "City": "Coimbatore",
    "Conc. name": "L&T",
    "Latitude": 10.914016,
    "Longitude": 76.982178
  },
  {
    "Plaza Code": 360021,
    "Plaza Name": "Pollachi Salem Toll\nPlaza",
    "Conc. Type": "Conc.",
    "Plaza Type": "TOLL",
    "Plaza Sub Type": "NATIONAL",
    "Sate": "Tamil Nadu",
    "City": "Coimbatore",
    "Conc. name": "L&T",
    "Latitude": 10.921531,
    "Longitude": 76.989327
  },
  {
    "Plaza Code": 360024,
    "Plaza Name": "Neelambur",
    "Conc. Type": "Conc.",
    "Plaza Type": "TOLL",
    "Plaza Sub Type": "NATIONAL",
    "Sate": "Tamil Nadu",
    "City": "Coimbatore",
    "Conc. name": "L&T",
    "Latitude": 11.060944,
    "Longitude": 77.088928
  },
  {
    "Plaza Code": 360025,
    "Plaza Name": "Trichy Salem",
    "Conc. Type": "Conc.",
    "Plaza Type": "TOLL",
    "Plaza Sub Type": "NATIONAL",
    "Sate": "Tamil Nadu",
    "City": "Coimbatore",
    "Conc. name": "L&T",
    "Latitude": 11.012859,
    "Longitude": 77.073174
  },
  {
    "Plaza Code": 360026,
    "Plaza Name": "Trichy Cochin",
    "Conc. Type": "Conc.",
    "Plaza Type": "TOLL",
    "Plaza Sub Type": "NATIONAL",
    "Sate": "Tamil Nadu",
    "City": "Coimbatore",
    "Conc. name": "L&T",
    "Latitude": 11.005088,
    "Longitude": 77.069038
  },
  {
    "Plaza Code": 360027,
    "Plaza Name": "Madukkarai",
    "Conc. Type": "Conc.",
    "Plaza Type": "TOLL",
    "Plaza Sub Type": "NATIONAL",
    "Sate": "Tamil Nadu",
    "City": "Coimbatore",
    "Conc. name": "L&T",
    "Latitude": 10.895638,
    "Longitude": 76.945815
  },
  {
    "Plaza Code": 360028,
    "Plaza Name": "SURAPATTU TOLL\nPLAZA",
    "Conc. Type": "PF",
    "Plaza Type": "TOLL",
    "Plaza Sub Type": "NATIONAL",
    "Sate": "Tamil Nadu",
    "City": "Tiruvallur",
    "Conc. name": "NHAI",
    "Latitude": 13.136678,
    "Longitude": 80.181624
  },
  {
    "Plaza Code": 360029,
    "Plaza Name": "Pattarai Toll Plaza",
    "Conc. Type": "PF",
    "Plaza Type": "TOLL",
    "Plaza Sub Type": "NATIONAL",
    "Sate": "Tamil Nadu",
    "City": "Tiruvallur",
    "Conc. name": "NHAI",
    "Latitude": 13.150829,
    "Longitude": 79.834687
  },
  {
    "Plaza Code": 360030,
    "Plaza Name": "Athur Toll Plaza",
    "Conc. Type": "PF",
    "Plaza Type": "TOLL",
    "Plaza Sub Type": "NATIONAL",
    "Sate": "Tamil Nadu",
    "City": "Kanchipuram",
    "Conc. name": "NHAI",
    "Latitude": 12.346862,
    "Longitude": 79.779856
  },
  {
    "Plaza Code": 360031,
    "Plaza Name": "SriPerumbadur",
    "Conc. Type": "PF",
    "Plaza Type": "TOLL",
    "Plaza Sub Type": "NATIONAL",
    "Sate": "Tamil Nadu",
    "City": "Kanchipuram",
    "Conc. name": "NHAI",
    "Latitude": 12.982155,
    "Longitude": 79.968944
  },
  {
    "Plaza Code": 360032,
    "Plaza Name": "Nallur Toll Plaza",
    "Conc. Type": "PF",
    "Plaza Type": "TOLL",
    "Plaza Sub Type": "NATIONAL",
    "Sate": "Tamil Nadu",
    "City": "Tiruvallur",
    "Conc. name": "L&T",
    "Latitude": 13.216958,
    "Longitude": 80.169353
  },
  {
    "Plaza Code": 360033,
    "Plaza Name": "Chennasamaduram\nToll Plaza",
    "Conc. Type": "PF",
    "Plaza Type": "TOLL",
    "Plaza Sub Type": "NATIONAL",
    "Sate": "Tamil Nadu",
    "City": "Vellore",
    "Conc. name": "NHAI",
    "Latitude": 12.910943,
    "Longitude": 79.40121
  },
  {
    "Plaza Code": 360034,
    "Plaza Name": "Vanagaram Toll Plaza",
    "Conc. Type": "PF",
    "Plaza Type": "TOLL",
    "Plaza Sub Type": "NATIONAL",
    "Sate": "Tamil Nadu",
    "City": "Tiruvallur",
    "Conc. name": "NHAI",
    "Latitude": 13.043526,
    "Longitude": 80.149598
  },
  {
    "Plaza Code": 360036,
    "Plaza Name": "VAGAIKULAM Toll\nPlaza",
    "Conc. Type": "PF",
    "Plaza Type": "TOLL",
    "Plaza Sub Type": "NATIONAL",
    "Sate": "Tamil Nadu",
    "City": "Thoothukudi",
    "Conc. name": "NHAI",
    "Latitude": 8.7362399,
    "Longitude": 78.0238105
  },
  {
    "Plaza Code": 360037,
    "Plaza Name": "Kappalur",
    "Conc. Type": "PF",
    "Plaza Type": "TOLL",
    "Plaza Sub Type": "NATIONAL",
    "Sate": "Tamil Nadu",
    "City": "Madurai",
    "Conc. name": "Raima\nToll\nRoad(ME\nP)",
    "Latitude": 9.844294,
    "Longitude": 78.011209
  },
  {
    "Plaza Code": 360039,
    "Plaza Name": "Nanguneri Toll Plaza",
    "Conc. Type": "PF",
    "Plaza Type": "TOLL",
    "Plaza Sub Type": "NATIONAL",
    "Sate": "Tamil Nadu",
    "City": "Tirunelveli",
    "Conc. name": "Raima\nToll\nRoad(ME\nP)",
    "Latitude": 8.527035,
    "Longitude": 77.663289
  },
  {
    "Plaza Code": 360040,
    "Plaza Name": "Etturvattam Toll\nPlaza",
    "Conc. Type": "PF",
    "Plaza Type": "TOLL",
    "Plaza Sub Type": "NATIONAL",
    "Sate": "Tamil Nadu",
    "City": "Virudhunagar",
    "Conc. name": "Raima\nToll\nRoad(ME\nP)",
    "Latitude": 9.385445,
    "Longitude": 77.914347
  },
  {
    "Plaza Code": 360041,
    "Plaza Name": "D C Palli Toll Plaza",
    "Conc. Type": "PF",
    "Plaza Type": "TOLL",
    "Plaza Sub Type": "NATIONAL",
    "Sate": "Tamil Nadu",
    "City": "Dharmavaram",
    "Conc. name": "NHAI",
    "Latitude": 14.6853947,
    "Longitude": 79.5155303
  },
  {
    "Plaza Code": 360042,
    "Plaza Name": "Mathur Toll Plaza",
    "Conc. Type": "PF",
    "Plaza Type": "TOLL",
    "Plaza Sub Type": "NATIONAL",
    "Sate": "Tamil Nadu",
    "City": "Madharam",
    "Conc. name": "NHAI",
    "Latitude": 13.1762697,
    "Longitude": 80.2447934
  },
  {
    "Plaza Code": 360043,
    "Plaza Name": "Chittampatti Toll\nPlaza",
    "Conc. Type": "PF",
    "Plaza Type": "TOLL",
    "Plaza Sub Type": "NATIONAL",
    "Sate": "Tamil Nadu",
    "City": "Madurai",
    "Conc. name": "M/s\nEagle\nInfra\nIndia Ltd",
    "Latitude": 9.989594,
    "Longitude": 78.244086
  },
  {
    "Plaza Code": 360044,
    "Plaza Name": "Buchireddypalem\nToll Plaza",
    "Conc. Type": "PF",
    "Plaza Type": "TOLL",
    "Plaza Sub Type": "NATIONAL",
    "Sate": "Tamil Nadu",
    "City": "Nellore",
    "Conc. name": "NHAI",
    "Latitude": 14.543497,
    "Longitude": 79.862213
  },
  {
    "Plaza Code": 360045,
    "Plaza Name": "Boothakudi Toll Plaza",
    "Conc. Type": "PF",
    "Plaza Type": "TOLL",
    "Plaza Sub Type": "NATIONAL",
    "Sate": "Tamil Nadu",
    "City": "Pudukkottai",
    "Conc. name": "M/s\nEagle\nInfra\nIndia Ltd",
    "Latitude": 10.64127,
    "Longitude": 78.581277
  },
  {
    "Plaza Code": 360046,
    "Plaza Name": "Bogalur",
    "Conc. Type": "PF",
    "Plaza Type": "TOLL",
    "Plaza Sub Type": "NATIONAL",
    "Sate": "Tamil Nadu",
    "City": "Ramnathpura\nm",
    "Conc. name": "NHAI",
    "Latitude": 9.3981517,
    "Longitude": 78.7140107
  },
  {
    "Plaza Code": 360047,
    "Plaza Name": "Tirupachethi",
    "Conc. Type": "PF",
    "Plaza Type": "TOLL",
    "Plaza Sub Type": "NATIONAL",
    "Sate": "Tamil Nadu",
    "City": "Sivagangai",
    "Conc. name": "NHAI",
    "Latitude": 9.780766,
    "Longitude": 78.335269
  },
  {
    "Plaza Code": 360048,
    "Plaza Name": "Palaya\nGandharvakottai",
    "Conc. Type": "PF",
    "Plaza Type": "TOLL",
    "Plaza Sub Type": "NATIONAL",
    "Sate": "Tamil Nadu",
    "City": "Palaya\nGandharvakot\ntaiÂxa0Village",
    "Conc. name": "NHAI",
    "Latitude": 10.6122581,
    "Longitude": 79.0305683
  },
  {
    "Plaza Code": 360049,
    "Plaza Name": "Paranur",
    "Conc. Type": "PF",
    "Plaza Type": "TOLL",
    "Plaza Sub Type": "NATIONAL",
    "Sate": "Tamil Nadu",
    "City": "Kanchipuram",
    "Conc. name": "NHAI",
    "Latitude": 12.723887,
    "Longitude": 79.981917
  },
  {
    "Plaza Code": 360050,
    "Plaza Name": "Lembalakudi",
    "Conc. Type": "PF",
    "Plaza Type": "TOLL",
    "Plaza Sub Type": "NATIONAL",
    "Sate": "Tamil Nadu",
    "City": "Pudukkottai",
    "Conc. name": "NHAI",
    "Latitude": 10.299776,
    "Longitude": 78.770713
  },
  {
    "Plaza Code": 360051,
    "Plaza Name": "Lechchumanapatti",
    "Conc. Type": "PF",
    "Plaza Type": "TOLL",
    "Plaza Sub Type": "NATIONAL",
    "Sate": "Tamil Nadu",
    "City": "Pudukkottai",
    "Conc. name": "NHAI",
    "Latitude": 10.624233,
    "Longitude": 78.747631
  },
  {
    "Plaza Code": 360054,
    "Plaza Name": "Shenbagampettai\nToll Plaza",
    "Conc. Type": "PF",
    "Plaza Type": "TOLL",
    "Plaza Sub Type": "NATIONAL",
    "Sate": "Tamil Nadu",
    "City": "Shenbagampe\nttai Village",
    "Conc. name": "NHAI",
    "Latitude": 10.1588453,
    "Longitude": 78.6509687
  },
  {
    "Plaza Code": 360058,
    "Plaza Name": "Keezhkuppam Toll\nPlaza",
    "Conc. Type": "PF.",
    "Plaza Type": "TOLL",
    "Plaza Sub Type": "NATIONAL",
    "Sate": "Tamil Nadu",
    "City": "Kallakurichi",
    "Conc. name": "NHAI",
    "Latitude": 12.3823,
    "Longitude": 78.8982
  },
  {
    "Plaza Code": 360059,
    "Plaza Name": "Ponnalagaram Toll\nPlaza",
    "Conc. Type": "PF.",
    "Plaza Type": "TOLL",
    "Plaza Sub Type": "NATIONAL",
    "Sate": "Tamil Nadu",
    "City": "Virudhachala\nm",
    "Conc. name": "NHAI",
    "Latitude": 9.9297,
    "Longitude": 78.1101
  },
  {
    "Plaza Code": 360060,
    "Plaza Name": "Kodikottai Toll Plaza",
    "Conc. Type": "PF",
    "Plaza Type": "TOLL",
    "Plaza Sub Type": "NATIONAL",
    "Sate": "Tamil Nadu",
    "City": "Manjani",
    "Conc. name": "MD\nYOUSUF\nALI",
    "Latitude": 9.887952,
    "Longitude": 78.8477
  },
  {
    "Plaza Code": 360062,
    "Plaza Name": "Kallakudi Toll plaza",
    "Conc. Type": "Conc.",
    "Plaza Type": "TOLL",
    "Plaza Sub Type": "NATIONAL",
    "Sate": "Tamil Nadu",
    "City": "Kallakudi",
    "Conc. name": "KNR\nSrirangam\nInfra Pvt\nLtd",
    "Latitude": 10.99696,
    "Longitude": 78.96709
  },
  {
    "Plaza Code": 360064,
    "Plaza Name": "Upparpatti",
    "Conc. Type": "PF",
    "Plaza Type": "TOLL",
    "Plaza Sub Type": "NATIONAL",
    "Sate": "Tamil Nadu",
    "City": "Upparpatti",
    "Conc. name": "NHAI",
    "Latitude": 9.942242,
    "Longitude": 77.419467
  },
  {
    "Plaza Code": 360065,
    "Plaza Name": "Vallam Toll Plaza",
    "Conc. Type": "PF",
    "Plaza Type": "TOLL",
    "Plaza Sub Type": "NATIONAL",
    "Sate": "Tamil Nadu",
    "City": "Tiruvannamala\ni",
    "Conc. name": "M/s Jai\nKamatana\nth &\nCompany",
    "Latitude": 12.744801,
    "Longitude": 79.151431
  },
  {
    "Plaza Code": 360066,
    "Plaza Name": "Enamkariyandal Toll\nPlaza",
    "Conc. Type": "PF",
    "Plaza Type": "TOLL",
    "Plaza Sub Type": "NATIONAL",
    "Sate": "Tamil Nadu",
    "City": "Tiruvannamala\ni",
    "Conc. name": "M/s Jai\nKamatana\nth &\nCompany",
    "Latitude": 12.287294,
    "Longitude": 79.06909
  },
  {
    "Plaza Code": 360067,
    "Plaza Name": "Thennamadevi Toll\nPlaza",
    "Conc. Type": "PF",
    "Plaza Type": "TOLL",
    "Plaza Sub Type": "NATIONAL",
    "Sate": "Tamil Nadu",
    "City": "Tiruvannamala\ni",
    "Conc. name": "M/s Jai\nKamatana\nth &\nCompany",
    "Latitude": 11.989279,
    "Longitude": 79.475046
  },
  {
    "Plaza Code": 360068,
    "Plaza Name": "Thirupathisaram Toll\nPlaza",
    "Conc. Type": "PF",
    "Plaza Type": "TOLL",
    "Plaza Sub Type": "NATIONAL",
    "Sate": "Tamil Nadu",
    "City": "Nagercoil",
    "Conc. name": "NHAI",
    "Latitude": 8.206201,
    "Longitude": 77.460289
  },
  {
    "Plaza Code": 360069,
    "Plaza Name": "Sevugampatti Toll\nPlaza",
    "Conc. Type": "PF",
    "Plaza Type": "TOLL",
    "Plaza Sub Type": "NATIONAL",
    "Sate": "Tamil Nadu",
    "City": "Sevugampatti",
    "Conc. name": "NHAI",
    "Latitude": 10.193994,
    "Longitude": 77.79427
  },
  {
    "Plaza Code": 367004,
    "Plaza Name": "Poonarimangalam",
    "Conc. Type": "PF",
    "Plaza Type": "TOLL",
    "Plaza Sub Type": "NATIONAL",
    "Sate": "Kerala",
    "City": "Ernakulam\n(Cochin)",
    "Conc. name": "NHAI",
    "Latitude": 10.010715,
    "Longitude": 76.257992
  },
  {
    "Plaza Code": 367006,
    "Plaza Name": "Thiruvallam Toll\nPlaza",
    "Conc. Type": "PF",
    "Plaza Type": "TOLL",
    "Plaza Sub Type": "NATIONAL",
    "Sate": "Kerala",
    "City": "Thiruvanantha\npuram",
    "Conc. name": "NHAI",
    "Latitude": 8.432799,
    "Longitude": 76.959632
  },
  {
    "Plaza Code": 367007,
    "Plaza Name": "Paniyankara Toll\nPlaza",
    "Conc. Type": "Conc.",
    "Plaza Type": "TOLL",
    "Plaza Sub Type": "NATIONAL",
    "Sate": "Kerala",
    "City": "Vadakkencher\nry",
    "Conc. name": "Thrissur\nExpreswa\ny Ltd",
    "Latitude": 10.590814,
    "Longitude": 76.458274
  },
  {
    "Plaza Code": 381000,
    "Plaza Name": "Managethi Toll Plaza",
    "Conc. Type": "PF",
    "Plaza Type": "TOLL",
    "Plaza Sub Type": "NATIONAL",
    "Sate": "Tamil Nadu",
    "City": "Ariyalur",
    "Conc. name": "Kallagam\nMeensuru\ntti Hwy\nPvt",
    "Latitude": 11.14185,
    "Longitude": 79.242155
  },
  {
    "Plaza Code": 536060,
    "Plaza Name": "Chatrapatti Toll Plaza",
    "Conc. Type": "PF",
    "Plaza Type": "TOLL",
    "Plaza Sub Type": "NATIONAL",
    "Sate": "Tamil Nadu",
    "City": "Dindigul",
    "Conc. name": "NHAI",
    "Latitude": 10.480588,
    "Longitude": 77.637335
  },
  {
    "Plaza Code": 536071,
    "Plaza Name": "Devikulam Plaza",
    "Conc. Type": "PF",
    "Plaza Type": "TOLL",
    "Plaza Sub Type": "NATIONAL",
    "Sate": "Kerala",
    "City": "Munnar",
    "Conc. name": "MD\nyousuf Ali",
    "Latitude": 10.056735,
    "Longitude": 77.104957
  },
  {
    "Plaza Code": 536087,
    "Plaza Name": "Thuvakudi Plaza",
    "Conc. Type": "PF",
    "Plaza Type": "TOLL",
    "Plaza Sub Type": "NATIONAL",
    "Sate": "Tamil Nadu",
    "City": "Thuvakudi",
    "Conc. name": "NHAI",
    "Latitude": 10.739075,
    "Longitude": 78.825026
  },
  {
    "Plaza Code": 536102,
    "Plaza Name": "Thiruvangad Toll\nPlaza",
    "Conc. Type": "PF",
    "Plaza Type": "TOLL",
    "Plaza Sub Type": "NATIONAL",
    "Sate": "Kerala",
    "City": "Thiruvangad\nVillage",
    "Conc. name": "M/s AV\nEnterpris\nes",
    "Latitude": 11.771619,
    "Longitude": 75.493803
  },
  {
    "Plaza Code": 536103,
    "Plaza Name": "Gangarampalayam\nToll Plaza",
    "Conc. Type": "PF",
    "Plaza Type": "TOLL",
    "Plaza Sub Type": "NATIONAL",
    "Sate": "Tamil Nadu",
    "City": "Villupuram",
    "Conc. name": "Dilip\nBuildcon\nLimited",
    "Latitude": 11.919673,
    "Longitude": 79.620412
  },
  {
    "Plaza Code": 536104,
    "Plaza Name": "Velampatti fee plaza",
    "Conc. Type": "PF",
    "Plaza Type": "TOLL",
    "Plaza Sub Type": "NATIONAL",
    "Sate": "Tamil Nadu",
    "City": "Tiruppur",
    "Conc. name": "NHAI",
    "Latitude": 10.99368,
    "Longitude": 77.41802
  },
  {
    "Plaza Code": 536109,
    "Plaza Name": "Kotthatai",
    "Conc. Type": "PF",
    "Plaza Type": "TOLL",
    "Plaza Sub Type": "NATIONAL",
    "Sate": "Tamil Nadu",
    "City": "Kothattai",
    "Conc. name": "M/s.\nGaneshga\nrhia",
    "Latitude": 11.51602,
    "Longitude": 79.71956
  },
  {
    "Plaza Code": 536183,
    "Plaza Name": "Linglapura",
    "Conc. Type": "PF",
    "Plaza Type": "TOLL",
    "Plaza Sub Type": "NATIONAL",
    "Sate": "Karnataka",
    "City": "Linglapura",
    "Conc. name": "M/s.\nABBRPL.",
    "Latitude": 13.44391,
    "Longitude": 76.13782
  },
  {
    "Plaza Code": 536198,
    "Plaza Name": "Hulikunte",
    "Conc. Type": "PF",
    "Plaza Type": "TOLL",
    "Plaza Sub Type": "NATIONAL",
    "Sate": "Karnataka",
    "City": "Bengaluru",
    "Conc. name": "NHAI",
    "Latitude": 13.271,
    "Longitude": 77.3475
  },
  {
    "Plaza Code": 536236,
    "Plaza Name": "Kurungudi",
    "Conc. Type": "PF",
    "Plaza Type": "TOLL",
    "Plaza Sub Type": "NATIONAL",
    "Sate": "Tamil Nadu",
    "City": "Kattumannark\noil",
    "Conc. name": "M/s Jai\nKamtanat\nh &\nCompany",
    "Latitude": 11.2678,
    "Longitude": 79.546
  },
  {
    "Plaza Code": 536246,
    "Plaza Name": "Kariyamanglam Toll\nPlaza",
    "Conc. Type": "PF",
    "Plaza Type": "TOLL",
    "Plaza Sub Type": "NATIONAL",
    "Sate": "Tamil Nadu",
    "City": "Tiruvannamala\ni",
    "Conc. name": "M/S\nRoopali\nJewellers",
    "Latitude": 12.2882726,
    "Longitude": 78.8285762
  },
  {
    "Plaza Code": 536382,
    "Plaza Name": "Nagampatti Toll\nPlaza",
    "Conc. Type": "PF",
    "Plaza Type": "TOLL",
    "Plaza Sub Type": "NATIONAL",
    "Sate": "Tamil Nadu",
    "City": "Krishnagiri",
    "Conc. name": "NHAI",
    "Latitude": 12.401124,
    "Longitude": 78.392165
  },
  {
    "Plaza Code": 536383,
    "Plaza Name": "Chowlagere Toll\nPlaza",
    "Conc. Type": "PF",
    "Plaza Type": "TOLL",
    "Plaza Sub Type": "NATIONAL",
    "Sate": "Karnataka",
    "City": "Hassan",
    "Conc. name": "NHAI",
    "Latitude": 12.963535,
    "Longitude": 75.99261
  },
  {
    "Plaza Code": 536385,
    "Plaza Name": "Naglikondan Toll\nPlaza",
    "Conc. Type": "PF",
    "Plaza Type": "TOLL",
    "Plaza Sub Type": "NATIONAL",
    "Sate": "Tamil Nadu",
    "City": "Gingee",
    "Conc. name": "PIU\nVillupura\nm",
    "Latitude": 12.253642,
    "Longitude": 79.466397
  },
  {
    "Plaza Code": 536392,
    "Plaza Name": "Painampalli Toll Plaza",
    "Conc. Type": "PF",
    "Plaza Type": "TOLL",
    "Plaza Sub Type": "NATIONAL",
    "Sate": "Telangana",
    "City": "Painampalli",
    "Conc. name": "NHAI",
    "Latitude": 17.0731,
    "Longitude": 80.0393
  },
  {
    "Plaza Code": 536397,
    "Plaza Name": "Medipally",
    "Conc. Type": "PF",
    "Plaza Type": "TOLL",
    "Plaza Sub Type": "NATIONAL",
    "Sate": "Telangana",
    "City": "Bhulapally",
    "Conc. name": "Coral\nAssociate\ns",
    "Latitude": 18.555458,
    "Longitude": 79.923521
  },
  {
    "Plaza Code": 536404,
    "Plaza Name": "Kadhavani Toll Plaza",
    "Conc. Type": "PF",
    "Plaza Type": "TOLL",
    "Plaza Sub Type": "NATIONAL",
    "Sate": "Tamil Nadu",
    "City": "Kannanur",
    "Conc. name": "Skylark\nInfra\nEngineeri\nng Pvt",
    "Latitude": 12.375194,
    "Longitude": 78.545639
  },
  {
    "Plaza Code": 536413,
    "Plaza Name": "Kovilvenni Toll Plaza",
    "Conc. Type": "PF",
    "Plaza Type": "TOLL",
    "Plaza Sub Type": "NATIONAL",
    "Sate": "Tamil Nadu",
    "City": "Thiruvarur",
    "Conc. name": "Ganeshgh\nargia\nConst Pvt\nLtd",
    "Latitude": 10.786021,
    "Longitude": 79.353558
  },
  {
    "Plaza Code": 536419,
    "Plaza Name": "Vembukudi",
    "Conc. Type": "PF",
    "Plaza Type": "TOLL",
    "Plaza Sub Type": "NATIONAL",
    "Sate": "Tamil Nadu",
    "City": "Papanasam",
    "Conc. name": "Ms\nNeeraj\nKumar",
    "Latitude": 10.874965,
    "Longitude": 79.211381
  },
  {
    "Plaza Code": 536422,
    "Plaza Name": "Mulawad Toll Plaza",
    "Conc. Type": "PF",
    "Plaza Type": "TOLL",
    "Plaza Sub Type": "NATIONAL",
    "Sate": "Karnataka",
    "City": "Bijapur",
    "Conc. name": "NHAI",
    "Latitude": 16.636787,
    "Longitude": 75.731832
  },
  {
    "Plaza Code": 536434,
    "Plaza Name": "H. Pudhupatti",
    "Conc. Type": "PF",
    "Plaza Type": "TOLL",
    "Plaza Sub Type": "NATIONAL",
    "Sate": "Tamil Nadu",
    "City": "Dharmapuri",
    "Conc. name": "NHAI",
    "Latitude": 11.96754,
    "Longitude": 78.42557
  },
  {
    "Plaza Code": 536450,
    "Plaza Name": "Mustapur",
    "Conc. Type": "PF",
    "Plaza Type": "TOLL",
    "Plaza Sub Type": "NATIONAL",
    "Sate": "Karnataka",
    "City": "Aurad",
    "Conc. name": "NHAI",
    "Latitude": 18.09738885,
    "Longitude": 77.45056418
  },
  {
    "Plaza Code": 536457,
    "Plaza Name": "Alagapada Toll Plaza",
    "Conc. Type": "PF",
    "Plaza Type": "TOLL",
    "Plaza Sub Type": "NATIONAL",
    "Sate": "Telangana",
    "City": "Miryalaguda",
    "Conc. name": "PIU\nAhmedna\ngar",
    "Latitude": 16.871519,
    "Longitude": 79.639311
  },
  {
    "Plaza Code": 536467,
    "Plaza Name": "Karagadahalli Toll\nPlaza",
    "Conc. Type": "PF",
    "Plaza Type": "TOLL",
    "Plaza Sub Type": "NATIONAL",
    "Sate": "Tamil Nadu",
    "City": "DHARMAPURI",
    "Conc. name": "DHARMA\nPURI\nInfra Pvt.\nLtd.",
    "Latitude": 12.260636,
    "Longitude": 78.090441
  },
  {
    "Plaza Code": 536482,
    "Plaza Name": "Sathyagala",
    "Conc. Type": "PF",
    "Plaza Type": "TOLL",
    "Plaza Sub Type": "NATIONAL",
    "Sate": "Karnataka",
    "City": "Bangalore",
    "Conc. name": "Neeraj\nKumar",
    "Latitude": 12.285128,
    "Longitude": 77.131438
  },
  {
    "Plaza Code": 546028,
    "Plaza Name": "Nalluru Devanahalli",
    "Conc. Type": "PF",
    "Plaza Type": "TOLL",
    "Plaza Sub Type": "NATIONAL",
    "Sate": "Karnataka",
    "City": "Bengaluru",
    "Conc. name": "NHAI",
    "Latitude": 13.206308,
    "Longitude": 77.765553
  },
  {
    "Plaza Code": 546041,
    "Plaza Name": "Sarandi",
    "Conc. Type": "PF",
    "Plaza Type": "TOLL",
    "Plaza Sub Type": "NATIONAL",
    "Sate": "Telangana",
    "City": "Randi",
    "Conc. name": "NHAI",
    "Latitude": 19.4514954672,
    "Longitude": 40479.3150453932
  },
  {
    "Plaza Code": 536044,
    "Plaza Name": "Sarasamba",
    "Conc. Type": "Concessio\nnaire",
    "Plaza Type": "TOLL",
    "Plaza Sub Type": "STATE",
    "Sate": "Karnataka",
    "City": "Kalaburagi",
    "Conc. name": "KRDCL",
    "Latitude": 17.5809346,
    "Longitude": 76.4218373
  },
  {
    "Plaza Code": 536045,
    "Plaza Name": "Pattana",
    "Conc. Type": "Concessio\nnaire",
    "Plaza Type": "TOLL",
    "Plaza Sub Type": "STATE",
    "Sate": "Karnataka",
    "City": "Kalaburagi",
    "Conc. name": "KRDCL",
    "Latitude": 17.3970162,
    "Longitude": 76.7061871
  },
  {
    "Plaza Code": 536046,
    "Plaza Name": "Sannur",
    "Conc. Type": "Concessio\nnaire",
    "Plaza Type": "TOLL",
    "Plaza Sub Type": "STATE",
    "Sate": "Karnataka",
    "City": "Kalaburagi",
    "Conc. name": "KRDCL",
    "Latitude": 17.2883106,
    "Longitude": 77.0015798
  },
  {
    "Plaza Code": 536047,
    "Plaza Name": "Jawahar Nagar",
    "Conc. Type": "Concessio\nnaire",
    "Plaza Type": "TOLL",
    "Plaza Sub Type": "STATE",
    "Sate": "Karnataka",
    "City": "Kalaburagi",
    "Conc. name": "KRDCL",
    "Latitude": 17.1287679,
    "Longitude": 77.3493783
  },
  {
    "Plaza Code": 536055,
    "Plaza Name": "NeoPolis",
    "Conc. Type": "BOT",
    "Plaza Type": "TOLL",
    "Plaza Sub Type": "STATE",
    "Sate": "Telangana",
    "City": "Hyderabad",
    "Conc. name": "IRB",
    "Latitude": 17.4107638888,
    "Longitude": 88978.3153361111
  },
  {
    "Plaza Code": 536056,
    "Plaza Name": "Mallampet",
    "Conc. Type": "BOT",
    "Plaza Type": "TOLL",
    "Plaza Sub Type": "STATE",
    "Sate": "Telangana",
    "City": "Hyderabad",
    "Conc. name": "IRB",
    "Latitude": 17.5609388888,
    "Longitude": 88978.3682
  },
  {
    "Plaza Code": 536062,
    "Plaza Name": "Moka Toll Plaza",
    "Conc. Type": "Conc.",
    "Plaza Type": "TOLL",
    "Plaza Sub Type": "STATE",
    "Sate": "Karnataka",
    "City": "Ashok Nagar",
    "Conc. name": "Bharathi\nConstruct\nions",
    "Latitude": 15.194774,
    "Longitude": 76.999231
  },
  {
    "Plaza Code": 536107,
    "Plaza Name": "Kallapura Toll Plaza",
    "Conc. Type": "Conc.",
    "Plaza Type": "TOLL",
    "Plaza Sub Type": "STATE",
    "Sate": "Karnataka",
    "City": "Bangalore",
    "Conc. name": "KRDCL",
    "Latitude": 14.0805,
    "Longitude": 75.5345
  },
  {
    "Plaza Code": 536125,
    "Plaza Name": "HEDIYALA TOLL\nPLAZA",
    "Conc. Type": "Conc.",
    "Plaza Type": "TOLL",
    "Plaza Sub Type": "STATE",
    "Sate": "Karnataka",
    "City": "Bangalore",
    "Conc. name": "KRDCL",
    "Latitude": 14.547139,
    "Longitude": 75.547111
  },
  {
    "Plaza Code": 536126,
    "Plaza Name": "HAMSABHAVI TOLL\nPLAZA",
    "Conc. Type": "Conc.",
    "Plaza Type": "TOLL",
    "Plaza Sub Type": "STATE",
    "Sate": "Karnataka",
    "City": "Bangalore",
    "Conc. name": "KRDCL",
    "Latitude": 14.561583,
    "Longitude": 75.346972
  },
  {
    "Plaza Code": 536127,
    "Plaza Name": "DANNUR TOLL PLAZA",
    "Conc. Type": "Conc.",
    "Plaza Type": "TOLL",
    "Plaza Sub Type": "STATE",
    "Sate": "Karnataka",
    "City": "Bangalore",
    "Conc. name": "KRDCL",
    "Latitude": 16.15425,
    "Longitude": 76.085778
  },
  {
    "Plaza Code": 536128,
    "Plaza Name": "DEVARAHULABAGAL\nTOLL PLAZA",
    "Conc. Type": "Conc.",
    "Plaza Type": "TOLL",
    "Plaza Sub Type": "STATE",
    "Sate": "Karnataka",
    "City": "Bangalore",
    "Conc. name": "KRDCL",
    "Latitude": 16.417556,
    "Longitude": 76.250806
  },
  {
    "Plaza Code": 536165,
    "Plaza Name": "Maddur Checkpost",
    "Conc. Type": "BOT",
    "Plaza Type": "TOLL",
    "Plaza Sub Type": "STATE",
    "Sate": "Karnataka",
    "City": "Gundlupet",
    "Conc. name": "Bandipur\ntiger\nreserve",
    "Latitude": 11.76904,
    "Longitude": 76.54773
  },
  {
    "Plaza Code": 536166,
    "Plaza Name": "G S Betta Checkpost",
    "Conc. Type": "BOT",
    "Plaza Type": "TOLL",
    "Plaza Sub Type": "STATE",
    "Sate": "Karnataka",
    "City": "Gundlupet",
    "Conc. name": "Bandipur\ntiger\nreserve",
    "Latitude": 11.720622,
    "Longitude": 76.580423
  },
  {
    "Plaza Code": 536167,
    "Plaza Name": "Kekkanahalla\ncheckpost",
    "Conc. Type": "BOT",
    "Plaza Type": "TOLL",
    "Plaza Sub Type": "STATE",
    "Sate": "Karnataka",
    "City": "Gundlupet",
    "Conc. name": "Bandipur\ntiger\nreserve",
    "Latitude": 11.618946,
    "Longitude": 76.590337
  },
  {
    "Plaza Code": 536350,
    "Plaza Name": "SKT Toll Plaza",
    "Conc. Type": "BOT",
    "Plaza Type": "TOLL",
    "Plaza Sub Type": "STATE",
    "Sate": "Karnataka",
    "City": "Sandur",
    "Conc. name": "Sandur\nBypass\nProject\nLtd.",
    "Latitude": 15.086331,
    "Longitude": 76.563406
  },
  {
    "Plaza Code": 536351,
    "Plaza Name": "Bhujanganagar Toll\nPlaza",
    "Conc. Type": "BOT",
    "Plaza Type": "TOLL",
    "Plaza Sub Type": "STATE",
    "Sate": "Karnataka",
    "City": "Sandur",
    "Conc. name": "Sandur\nBypass\nProject\nLtd.",
    "Latitude": 15.076736,
    "Longitude": 76.559806
  },
  {
    "Plaza Code": 536352,
    "Plaza Name": "Babaiya toll Plaza",
    "Conc. Type": "BOT",
    "Plaza Type": "TOLL",
    "Plaza Sub Type": "STATE",
    "Sate": "Karnataka",
    "City": "Sandur",
    "Conc. name": "Sandur\nBypass\nProject\nLtd.",
    "Latitude": 15.101522,
    "Longitude": 76.571192
  },
  {
    "Plaza Code": 536353,
    "Plaza Name": "ZP Road Toll Plaza",
    "Conc. Type": "BOT",
    "Plaza Type": "TOLL",
    "Plaza Sub Type": "STATE",
    "Sate": "Karnataka",
    "City": "Sandur",
    "Conc. name": "Sandur\nBypass\nProject\nLtd.",
    "Latitude": 15.108936,
    "Longitude": 76.570494
  },
  {
    "Plaza Code": 536354,
    "Plaza Name": "Hosapete Bypass\nToll Plaza",
    "Conc. Type": "BOT",
    "Plaza Type": "TOLL",
    "Plaza Sub Type": "STATE",
    "Sate": "Karnataka",
    "City": "Sandur",
    "Conc. name": "Sandur\nBypass\nProject\nLtd.",
    "Latitude": 15.110119,
    "Longitude": 76.515472
  },
  {
    "Plaza Code": 536355,
    "Plaza Name": "Dharmapur Toll Plaza",
    "Conc. Type": "BOT",
    "Plaza Type": "TOLL",
    "Plaza Sub Type": "STATE",
    "Sate": "Karnataka",
    "City": "Sandur",
    "Conc. name": "Sandur\nBypass\nProject\nLtd.",
    "Latitude": 15.064975,
    "Longitude": 76.528664
  },
  {
    "Plaza Code": 536387,
    "Plaza Name": "Bettal Thanda",
    "Conc. Type": "BOT",
    "Plaza Type": "TOLL",
    "Plaza Sub Type": "STATE",
    "Sate": "Telangana",
    "City": "Nagarjunasaga\nr",
    "Conc. name": "Telangan\na Forest\nDepartme\nnt",
    "Latitude": 16.61742,
    "Longitude": 79.29566
  },
  {
    "Plaza Code": 536388,
    "Plaza Name": "Nellikal",
    "Conc. Type": "BOT",
    "Plaza Type": "TOLL",
    "Plaza Sub Type": "STATE",
    "Sate": "Telangana",
    "City": "Nagarjunasaga\nr",
    "Conc. name": "Telangan\na Forest\nDepartme\nnt",
    "Latitude": 16.67119,
    "Longitude": 79.28775
  },
  {
    "Plaza Code": 536389,
    "Plaza Name": "FDO Complex",
    "Conc. Type": "BOT",
    "Plaza Type": "TOLL",
    "Plaza Sub Type": "STATE",
    "Sate": "Telangana",
    "City": "Nagarjunasaga\nr",
    "Conc. name": "Telangan\na Forest\nDepartme\nnt",
    "Latitude": 16.6723,
    "Longitude": 79.27726
  },
  {
    "Plaza Code": 536437,
    "Plaza Name": "Chakenahalli Toll\nPlaza",
    "Conc. Type": "Conc.",
    "Plaza Type": "TOLL",
    "Plaza Sub Type": "STATE",
    "Sate": "Karnataka",
    "City": "Chakenahalli",
    "Conc. name": "Lighthous\ne\nConstruct\nions",
    "Latitude": 12.9824,
    "Longitude": 76.8837
  },
  {
    "Plaza Code": 536474,
    "Plaza Name": "Chinnar 9/6\ncheckpost",
    "Conc. Type": "BOT",
    "Plaza Type": "TOLL",
    "Plaza Sub Type": "STATE",
    "Sate": "Tamil Nadu",
    "City": "Chinnar",
    "Conc. name": "Anamalai\nTiger\nReserve",
    "Latitude": 10.44963,
    "Longitude": 77.240929
  },
  {
    "Plaza Code": 536478,
    "Plaza Name": "Jalahalli Toll Plaza",
    "Conc. Type": "Conc",
    "Plaza Type": "TOLL",
    "Plaza Sub Type": "STATE",
    "Sate": "Karnataka",
    "City": "Jalahalli",
    "Conc. name": "Bharthi\nConstruct\nion-\nKRDCL",
    "Latitude": 16.3711,
    "Longitude": 76.7678
  },
  {
    "Plaza Code": 536479,
    "Plaza Name": "Kakargal Toll Plaza",
    "Conc. Type": "Conc",
    "Plaza Type": "TOLL",
    "Plaza Sub Type": "STATE",
    "Sate": "Karnataka",
    "City": "Kakargal",
    "Conc. name": "Bharthi\nConstruct\nion-\nKRDCL",
    "Latitude": 16.3367,
    "Longitude": 77.0619
  },
  {
    "Plaza Code": 550001,
    "Plaza Name": "Kokapet",
    "Conc. Type": "PF",
    "Plaza Type": "TOLL",
    "Plaza Sub Type": "STATE",
    "Sate": "Telangana",
    "City": "Hyderabad",
    "Conc. name": "IRB",
    "Latitude": 17.242673,
    "Longitude": 78.194936
  },
  {
    "Plaza Code": 550002,
    "Plaza Name": "Edulanagulapally",
    "Conc. Type": "PF",
    "Plaza Type": "TOLL",
    "Plaza Sub Type": "STATE",
    "Sate": "Telangana",
    "City": "Hyderabad",
    "Conc. name": "IRB",
    "Latitude": 17.4622136,
    "Longitude": 78.2494394
  },
  {
    "Plaza Code": 550003,
    "Plaza Name": "Patancheru",
    "Conc. Type": "PF",
    "Plaza Type": "TOLL",
    "Plaza Sub Type": "STATE",
    "Sate": "Telangana",
    "City": "Hyderabad",
    "Conc. name": "IRB",
    "Latitude": 17.321673,
    "Longitude": 78.140518
  },
  {
    "Plaza Code": 550004,
    "Plaza Name": "Sultanpur",
    "Conc. Type": "PF",
    "Plaza Type": "TOLL",
    "Plaza Sub Type": "STATE",
    "Sate": "Telangana",
    "City": "Hyderabad",
    "Conc. name": "IRB",
    "Latitude": 17.333045,
    "Longitude": 78.184737
  },
  {
    "Plaza Code": 550005,
    "Plaza Name": "Dundigal",
    "Conc. Type": "PF",
    "Plaza Type": "TOLL",
    "Plaza Sub Type": "STATE",
    "Sate": "Telangana",
    "City": "Hyderabad",
    "Conc. name": "IRB",
    "Latitude": 17.353843,
    "Longitude": 78.242823
  },
  {
    "Plaza Code": 550006,
    "Plaza Name": "Medchal",
    "Conc. Type": "PF",
    "Plaza Type": "TOLL",
    "Plaza Sub Type": "STATE",
    "Sate": "Telangana",
    "City": "Hyderabad",
    "Conc. name": "IRB",
    "Latitude": 17.355345,
    "Longitude": 78.292706
  },
  {
    "Plaza Code": 550007,
    "Plaza Name": "Shamirpet",
    "Conc. Type": "PF",
    "Plaza Type": "TOLL",
    "Plaza Sub Type": "STATE",
    "Sate": "Telangana",
    "City": "Hyderabad",
    "Conc. name": "IRB",
    "Latitude": 17.343361,
    "Longitude": 78.341763
  },
  {
    "Plaza Code": 550009,
    "Plaza Name": "Ghatkesar",
    "Conc. Type": "PF",
    "Plaza Type": "TOLL",
    "Plaza Sub Type": "STATE",
    "Sate": "Telangana",
    "City": "Hyderabad",
    "Conc. name": "IRB",
    "Latitude": 17.263039,
    "Longitude": 78.400211
  },
  {
    "Plaza Code": 550010,
    "Plaza Name": "Taramatipet",
    "Conc. Type": "PF",
    "Plaza Type": "TOLL",
    "Plaza Sub Type": "STATE",
    "Sate": "Telangana",
    "City": "Hyderabad",
    "Conc. name": "IRB",
    "Latitude": 17.222251,
    "Longitude": 78.40529
  },
  {
    "Plaza Code": 550011,
    "Plaza Name": "Pedda Amberpet",
    "Conc. Type": "PF",
    "Plaza Type": "TOLL",
    "Plaza Sub Type": "STATE",
    "Sate": "Telangana",
    "City": "Hyderabad",
    "Conc. name": "IRB",
    "Latitude": 17.319992,
    "Longitude": 78.655881
  },
  {
    "Plaza Code": 550012,
    "Plaza Name": "Bongulur",
    "Conc. Type": "PF",
    "Plaza Type": "TOLL",
    "Plaza Sub Type": "STATE",
    "Sate": "Telangana",
    "City": "Hyderabad",
    "Conc. name": "IRB",
    "Latitude": 17.141561,
    "Longitude": 78.350437
  },
  {
    "Plaza Code": 550013,
    "Plaza Name": "Ravi Ryal",
    "Conc. Type": "PF",
    "Plaza Type": "TOLL",
    "Plaza Sub Type": "STATE",
    "Sate": "Telangana",
    "City": "Hyderabad",
    "Conc. name": "IRB",
    "Latitude": 17.124448,
    "Longitude": 78.313874
  },
  {
    "Plaza Code": 550014,
    "Plaza Name": "Tukkuguda",
    "Conc. Type": "PF",
    "Plaza Type": "TOLL",
    "Plaza Sub Type": "STATE",
    "Sate": "Telangana",
    "City": "Hyderabad",
    "Conc. name": "IRB",
    "Latitude": 17.121063,
    "Longitude": 78.283524
  },
  {
    "Plaza Code": 550015,
    "Plaza Name": "Peddagolconda",
    "Conc. Type": "PF",
    "Plaza Type": "TOLL",
    "Plaza Sub Type": "STATE",
    "Sate": "Telangana",
    "City": "Hyderabad",
    "Conc. name": "IRB",
    "Latitude": 17.121417,
    "Longitude": 78.235572
  },
  {
    "Plaza Code": 550016,
    "Plaza Name": "Shamshabad",
    "Conc. Type": "PF",
    "Plaza Type": "TOLL",
    "Plaza Sub Type": "STATE",
    "Sate": "Telangana",
    "City": "Hyderabad",
    "Conc. name": "IRB",
    "Latitude": 17.151163,
    "Longitude": 78.224438
  },
  {
    "Plaza Code": 550017,
    "Plaza Name": "Rajendra Nagar",
    "Conc. Type": "PF",
    "Plaza Type": "TOLL",
    "Plaza Sub Type": "STATE",
    "Sate": "Telangana",
    "City": "Hyderabad",
    "Conc. name": "IRB",
    "Latitude": 17.192464,
    "Longitude": 78.22308
  },
  {
    "Plaza Code": 550018,
    "Plaza Name": "TSPA",
    "Conc. Type": "PF",
    "Plaza Type": "TOLL",
    "Plaza Sub Type": "STATE",
    "Sate": "Telangana",
    "City": "Hyderabad",
    "Conc. name": "IRB",
    "Latitude": 17.210101,
    "Longitude": 78.214002
  },
  {
    "Plaza Code": 550019,
    "Plaza Name": "Nanakramguda",
    "Conc. Type": "PF",
    "Plaza Type": "TOLL",
    "Plaza Sub Type": "STATE",
    "Sate": "Telangana",
    "City": "Hyderabad",
    "Conc. name": "IRB",
    "Latitude": 17.242648,
    "Longitude": 78.211582
  },
  {
    "Plaza Code": 550020,
    "Plaza Name": "Duddeda Toll Plaza",
    "Conc. Type": "Conc.",
    "Plaza Type": "TOLL",
    "Plaza Sub Type": "STATE",
    "Sate": "Telangana",
    "City": "Medak",
    "Conc. name": "HKR\nROADWA\nYS",
    "Latitude": 18.0002,
    "Longitude": 78.8876
  },
  {
    "Plaza Code": 550021,
    "Plaza Name": "Renikunta Toll Plaza",
    "Conc. Type": "Conc.",
    "Plaza Type": "TOLL",
    "Plaza Sub Type": "STATE",
    "Sate": "Telangana",
    "City": "Karimnagar",
    "Conc. name": "HKR\nROADWA\nYS",
    "Latitude": 18.2943,
    "Longitude": 79.1171
  },
  {
    "Plaza Code": 550022,
    "Plaza Name": "Basanthnagar Toll\nPlaza",
    "Conc. Type": "Conc.",
    "Plaza Type": "TOLL",
    "Plaza Sub Type": "STATE",
    "Sate": "Telangana",
    "City": "Karimnagar",
    "Conc. name": "HKR\nROADWA\nYS",
    "Latitude": 18.7042,
    "Longitude": 79.417
  },
  {
    "Plaza Code": 550023,
    "Plaza Name": "Madugulapally TOLL\nPLAZA",
    "Conc. Type": "DBFOT",
    "Plaza Type": "TOLL",
    "Plaza Sub Type": "STATE",
    "Sate": "Telangana",
    "City": "Madugulapally",
    "Conc. name": "N.A.M.Ex\npressway",
    "Latitude": 16.9794,
    "Longitude": 79.4537
  },
  {
    "Plaza Code": 556001,
    "Plaza Name": "Kadathanamale Toll\nPlaza",
    "Conc. Type": "Conc.",
    "Plaza Type": "TOLL",
    "Plaza Sub Type": "STATE",
    "Sate": "Karnataka",
    "City": "Bangalore",
    "Conc. name": "YELAHAN\nKA AP\nBORDER\nTOLLWAY\nS",
    "Latitude": 13.2123515,
    "Longitude": 77.5535138
  },
  {
    "Plaza Code": 556002,
    "Plaza Name": "Gunjur Toll Plaza",
    "Conc. Type": "Conc.",
    "Plaza Type": "TOLL",
    "Plaza Sub Type": "STATE",
    "Sate": "Karnataka",
    "City": "Bangalore",
    "Conc. name": "YELAHAN\nKA AP\nBORDER\nTOLLWAY\nS",
    "Latitude": 13.4293608,
    "Longitude": 77.5124912
  },
  {
    "Plaza Code": 556003,
    "Plaza Name": "BYADARAHALLI TOLL\nPLAZA",
    "Conc. Type": "Conc.",
    "Plaza Type": "TOLL",
    "Plaza Sub Type": "STATE",
    "Sate": "Karnataka",
    "City": "GORUR",
    "Conc. name": "MITRA\nINFRA\nSOLUTIO\nNS",
    "Latitude": 12.521607,
    "Longitude": 76.041609
  },
  {
    "Plaza Code": 556004,
    "Plaza Name": "NILAVAGILU TOLL\nPLAZA",
    "Conc. Type": "Conc.",
    "Plaza Type": "TOLL",
    "Plaza Sub Type": "STATE",
    "Sate": "Karnataka",
    "City": "RAMANATHAP\nURA",
    "Conc. name": "MITRA\nINFRA\nSOLUTIO\nNS",
    "Latitude": 12.6657789,
    "Longitude": 76.0879545
  },
  {
    "Plaza Code": 556005,
    "Plaza Name": "COORGAL TOLL\nPLAZA",
    "Conc. Type": "Conc.",
    "Plaza Type": "TOLL",
    "Plaza Sub Type": "STATE",
    "Sate": "Karnataka",
    "City": "BETTADAPURA",
    "Conc. name": "MITRA\nINFRA\nSOLUTIO\nNS",
    "Latitude": 12.4421692,
    "Longitude": 76.1016017
  },
  {
    "Plaza Code": 556006,
    "Plaza Name": "GUDEMARANAHALLI\nTOLL PLAZA",
    "Conc. Type": "Conc.",
    "Plaza Type": "TOLL",
    "Plaza Sub Type": "STATE",
    "Sate": "Karnataka",
    "City": "MAGADI",
    "Conc. name": "MITRA\nINFRA\nSOLUTIO\nNS",
    "Latitude": 13.022707,
    "Longitude": 77.153308
  },
  {
    "Plaza Code": 556007,
    "Plaza Name": "TUMBADI TOLL\nPLAZA",
    "Conc. Type": "Conc.",
    "Plaza Type": "TOLL",
    "Plaza Sub Type": "STATE",
    "Sate": "Karnataka",
    "City": "KORATAGERE",
    "Conc. name": "MITRA\nINFRA\nSOLUTIO\nNS",
    "Latitude": 13.344609,
    "Longitude": 77.142203
  },
  {
    "Plaza Code": 556008,
    "Plaza Name": "BUDDAREDDYHALLI\nTOLL PLAZA",
    "Conc. Type": "Conc.",
    "Plaza Type": "TOLL",
    "Plaza Sub Type": "STATE",
    "Sate": "Karnataka",
    "City": "PAVAGADA",
    "Conc. name": "MITRA\nINFRA\nSOLUTIO\nNS",
    "Latitude": 14.121006,
    "Longitude": 77.153804
  },
  {
    "Plaza Code": 556009,
    "Plaza Name": "DODDAMAVATHURU\nTOLL PLAZA",
    "Conc. Type": "Conc.",
    "Plaza Type": "TOLL",
    "Plaza Sub Type": "STATE",
    "Sate": "Karnataka",
    "City": "NEAR\nHULIYOORDU\nRGA",
    "Conc. name": "MITRA\nINFRA\nSOLUTIO\nNS",
    "Latitude": 12.533502,
    "Longitude": 77.024003
  },
  {
    "Plaza Code": 556010,
    "Plaza Name": "OBALAPURA TOLL\nPLAZA",
    "Conc. Type": "Conc.",
    "Plaza Type": "TOLL",
    "Plaza Sub Type": "STATE",
    "Sate": "Karnataka",
    "City": "NEAR\nYALLAPURA",
    "Conc. name": "MITRA\nINFRA\nSOLUTIO\nNS",
    "Latitude": 13.261002,
    "Longitude": 77.093901
  },
  {
    "Plaza Code": 556011,
    "Plaza Name": "Sherewada Toll Plaza",
    "Conc. Type": "Conc.",
    "Plaza Type": "TOLL",
    "Plaza Sub Type": "STATE",
    "Sate": "Karnataka",
    "City": "Kundagol",
    "Conc. name": "MITRA\nINFRA\nSOLUTIO\nNS",
    "Latitude": 15.260165,
    "Longitude": 75.177026
  },
  {
    "Plaza Code": 556013,
    "Plaza Name": "Tippanal Toll Plaza",
    "Conc. Type": "Conc.",
    "Plaza Type": "TOLL",
    "Plaza Sub Type": "STATE",
    "Sate": "Karnataka",
    "City": "Kanakagiri",
    "Conc. name": "MITRA\nINFRA\nSOLUTIO\nNS",
    "Latitude": 15.542704,
    "Longitude": 76.447683
  },
  {
    "Plaza Code": 556014,
    "Plaza Name": "Papanashi",
    "Conc. Type": "Conc.",
    "Plaza Type": "TOLL",
    "Plaza Sub Type": "STATE",
    "Sate": "Karnataka",
    "City": "Avadi\nSomapur",
    "Conc. name": "Kesar\nInvestme\nnt\nSecurities",
    "Latitude": 15.3582487,
    "Longitude": 75.6863757
  },
  {
    "Plaza Code": 556015,
    "Plaza Name": "Hiremannapur Toll\nPlaza",
    "Conc. Type": "Conc",
    "Plaza Type": "TOLL",
    "Plaza Sub Type": "STATE",
    "Sate": "Karnataka",
    "City": "Hiremannapur",
    "Conc. name": "Kesar\nInvestme\nnt\nSecurities",
    "Latitude": 15.7729777,
    "Longitude": 76.2985608
  },
  {
    "Plaza Code": 556016,
    "Plaza Name": "Hemagudda Toll\nPlaza",
    "Conc. Type": "DBFOT",
    "Plaza Type": "TOLL",
    "Plaza Sub Type": "STATE",
    "Sate": "Karnataka",
    "City": "Hemagudda\nVillage",
    "Conc. name": "Sindhanur\nGangavat\nhi",
    "Latitude": 15.431844,
    "Longitude": 76.405685
  },
  {
    "Plaza Code": 556017,
    "Plaza Name": "Marali",
    "Conc. Type": "DBFOT",
    "Plaza Type": "TOLL",
    "Plaza Sub Type": "STATE",
    "Sate": "Karnataka",
    "City": "Marali Village",
    "Conc. name": "Sindhanur\nGangavat\nhi",
    "Latitude": 15.4669393,
    "Longitude": 76.5742425
  },
  {
    "Plaza Code": 556018,
    "Plaza Name": "Kurki Toll Plaza",
    "Conc. Type": "Conc.",
    "Plaza Type": "TOLL",
    "Plaza Sub Type": "STATE",
    "Sate": "Karnataka",
    "City": "Kurki Village",
    "Conc. name": "LEJONET\nITS Tech",
    "Latitude": 14.351626,
    "Longitude": 75.979384
  },
  {
    "Plaza Code": 556019,
    "Plaza Name": "Javoor Toll Plaza",
    "Conc. Type": "Conc.",
    "Plaza Type": "TOLL",
    "Plaza Sub Type": "STATE",
    "Sate": "Karnataka",
    "City": "Javoor Village",
    "Conc. name": "LEJONET\nITS Tech",
    "Latitude": 13.794751,
    "Longitude": 75.982067
  },
  {
    "Plaza Code": 556020,
    "Plaza Name": "Kamthana Toll Plaza",
    "Conc. Type": "PF",
    "Plaza Type": "TOLL",
    "Plaza Sub Type": "STATE",
    "Sate": "Karnataka",
    "City": "Bidar",
    "Conc. name": "JKL Stone",
    "Latitude": 17.845891,
    "Longitude": 77.448414
  },
  {
    "Plaza Code": 556021,
    "Plaza Name": "Ainoli Toll Plaza",
    "Conc. Type": "PF",
    "Plaza Type": "TOLL",
    "Plaza Sub Type": "STATE",
    "Sate": "Karnataka",
    "City": "Chincholi",
    "Conc. name": "JKL Stone",
    "Latitude": 17.503027,
    "Longitude": 77.431011
  },
  {
    "Plaza Code": 556022,
    "Plaza Name": "Chinchani plaza",
    "Conc. Type": "Conc",
    "Plaza Type": "TOLL",
    "Plaza Sub Type": "STATE",
    "Sate": "Karnataka",
    "City": "Chikodi",
    "Conc. name": "Vinay Lad\nEnterpris\nes",
    "Latitude": 16.418376,
    "Longitude": 74.540661
  },
  {
    "Plaza Code": 556023,
    "Plaza Name": "Kabbur plaza",
    "Conc. Type": "Conc",
    "Plaza Type": "TOLL",
    "Plaza Sub Type": "STATE",
    "Sate": "Karnataka",
    "City": "Chikodi",
    "Conc. name": "Vinay Lad\nEnterpris\nes",
    "Latitude": 16.359437,
    "Longitude": 74.701976
  },
  {
    "Plaza Code": 556024,
    "Plaza Name": "Link Road (L1) Toll",
    "Conc. Type": "Conc",
    "Plaza Type": "TOLL",
    "Plaza Sub Type": "STATE",
    "Sate": "Karnataka",
    "City": "Bengaluru",
    "Conc. name": "Nandi\nEconomic\nCorridor",
    "Latitude": 12.936583,
    "Longitude": 77.5315
  },
  {
    "Plaza Code": 556025,
    "Plaza Name": "Hosur Road (P1) Toll",
    "Conc. Type": "Conc",
    "Plaza Type": "TOLL",
    "Plaza Sub Type": "STATE",
    "Sate": "Karnataka",
    "City": "Bengaluru",
    "Conc. name": "Nandi\nEconomic\nCorridor",
    "Latitude": 12.858667,
    "Longitude": 77.655833
  },
  {
    "Plaza Code": 556027,
    "Plaza Name": "Bannerghatta Road\n(P2) Plaza",
    "Conc. Type": "Conc",
    "Plaza Type": "TOLL",
    "Plaza Sub Type": "STATE",
    "Sate": "Karnataka",
    "City": "Bengaluru",
    "Conc. name": "Nandi\nEconomic\nCorridor",
    "Latitude": 12.850056,
    "Longitude": 77.588333
  },
  {
    "Plaza Code": 556028,
    "Plaza Name": "Kanakapura Road\n(P3) Plaza",
    "Conc. Type": "Conc",
    "Plaza Type": "TOLL",
    "Plaza Sub Type": "STATE",
    "Sate": "Karnataka",
    "City": "Bengaluru",
    "Conc. name": "Nandi\nEconomic\nCorridor",
    "Latitude": 12.857833,
    "Longitude": 77.527583
  },
  {
    "Plaza Code": 556029,
    "Plaza Name": "Clever Leaf (P4) Plaza",
    "Conc. Type": "Conc",
    "Plaza Type": "TOLL",
    "Plaza Sub Type": "STATE",
    "Sate": "Karnataka",
    "City": "Bengaluru",
    "Conc. name": "Nandi\nEconomic\nCorridor",
    "Latitude": 12.884139,
    "Longitude": 77.501694
  },
  {
    "Plaza Code": 556030,
    "Plaza Name": "Mysore Road (P5)\nPlaza",
    "Conc. Type": "Conc",
    "Plaza Type": "TOLL",
    "Plaza Sub Type": "STATE",
    "Sate": "Karnataka",
    "City": "Bengaluru",
    "Conc. name": "Nandi\nEconomic\nCorridor",
    "Latitude": 12.903583,
    "Longitude": 77.470028
  },
  {
    "Plaza Code": 556031,
    "Plaza Name": "Magadi Road (P6)\nPlaza",
    "Conc. Type": "Conc",
    "Plaza Type": "TOLL",
    "Plaza Sub Type": "STATE",
    "Sate": "Karnataka",
    "City": "Bengaluru",
    "Conc. name": "Nandi\nEconomic\nCorridor",
    "Latitude": 12.989944,
    "Longitude": 77.472444
  },
  {
    "Plaza Code": 556032,
    "Plaza Name": "Harpanahalli Toll\nPlaza",
    "Conc. Type": "Conc.",
    "Plaza Type": "TOLL",
    "Plaza Sub Type": "STATE",
    "Sate": "Karnataka",
    "City": "Hadagali",
    "Conc. name": "NHAI",
    "Latitude": 14.806217,
    "Longitude": 75.975065
  },
  {
    "Plaza Code": 556033,
    "Plaza Name": "Mundaragi Toll Plaza",
    "Conc. Type": "Conc.",
    "Plaza Type": "TOLL",
    "Plaza Sub Type": "STATE",
    "Sate": "Karnataka",
    "City": "Mundargi",
    "Conc. name": "NHAI",
    "Latitude": 15.138206,
    "Longitude": 75.889905
  },
  {
    "Plaza Code": 556034,
    "Plaza Name": "Sanikoppa Toll Plaza",
    "Conc. Type": "Conc.",
    "Plaza Type": "TOLL",
    "Plaza Sub Type": "STATE",
    "Sate": "Karnataka",
    "City": "Bailhongal",
    "Conc. name": "JYOTHI\nPRAKSH\nKM",
    "Latitude": 15.800694,
    "Longitude": 74.804861
  },
  {
    "Plaza Code": 556035,
    "Plaza Name": "Karikatti Toll Plaza",
    "Conc. Type": "Conc.",
    "Plaza Type": "TOLL",
    "Plaza Sub Type": "STATE",
    "Sate": "Karnataka",
    "City": "Soundatti",
    "Conc. name": "JYOTHI\nPRAKSH\nKM",
    "Latitude": 15.738306,
    "Longitude": 75.063639
  },
  {
    "Plaza Code": 556041,
    "Plaza Name": "Beechagondanahalli",
    "Conc. Type": "Conc.",
    "Plaza Type": "TOLL",
    "Plaza Sub Type": "STATE",
    "Sate": "Karnataka",
    "City": "Beechagondan\nahalli",
    "Conc. name": "KRDCL",
    "Latitude": 13.263241,
    "Longitude": 77.944733
  },
  {
    "Plaza Code": 556042,
    "Plaza Name": "Aminbhavi Toll Plaza",
    "Conc. Type": "Conc.",
    "Plaza Type": "TOLL",
    "Plaza Sub Type": "STATE",
    "Sate": "Karnataka",
    "City": "Dharwad",
    "Conc. name": "NG\nINFOTECH",
    "Latitude": 15.528545,
    "Longitude": 75.049936
  },
  {
    "Plaza Code": 556043,
    "Plaza Name": "Narsingi",
    "Conc. Type": "BOT",
    "Plaza Type": "TOLL",
    "Plaza Sub Type": "STATE",
    "Sate": "Telangana",
    "City": "Hyderabad",
    "Conc. name": "HGCL",
    "Latitude": 17.388444,
    "Longitude": 78.351798
  },
  {
    "Plaza Code": 556045,
    "Plaza Name": "Yashwantpur Toll\nPlaza",
    "Conc. Type": "Conc.",
    "Plaza Type": "TOLL",
    "Plaza Sub Type": "STATE",
    "Sate": "Karnataka",
    "City": "Sandur",
    "Conc. name": "Madarasa\nb\nSinganam\nalli",
    "Latitude": 15.051567,
    "Longitude": 76.508268
  },
  {
    "Plaza Code": 556046,
    "Plaza Name": "Baneti Toll Plaza",
    "Conc. Type": "Conc.",
    "Plaza Type": "TOLL",
    "Plaza Sub Type": "STATE",
    "Sate": "Karnataka",
    "City": "Sandur",
    "Conc. name": "Madarasa\nb\nSinganam\nalli",
    "Latitude": 15.1520743,
    "Longitude": 76.6083795
  },
  {
    "Plaza Code": 560001,
    "Plaza Name": "Perungudi Toll Plaza",
    "Conc. Type": "PF",
    "Plaza Type": "TOLL",
    "Plaza Sub Type": "STATE",
    "Sate": "Tamil Nadu",
    "City": "Chennai",
    "Conc. name": "TNRDC",
    "Latitude": 12.9564,
    "Longitude": 80.2412
  },
  {
    "Plaza Code": 560002,
    "Plaza Name": "Central Server Toll\nPlaza",
    "Conc. Type": "PF",
    "Plaza Type": "TOLL",
    "Plaza Sub Type": "STATE",
    "Sate": "Tamil Nadu",
    "City": "Chennai",
    "Conc. name": "TNRDC",
    "Latitude": 12.9564,
    "Longitude": 80.2412
  },
  {
    "Plaza Code": 560003,
    "Plaza Name": "Thoraipakkam Toll\nPlaza",
    "Conc. Type": "PF",
    "Plaza Type": "TOLL",
    "Plaza Sub Type": "STATE",
    "Sate": "Tamil Nadu",
    "City": "Chennai",
    "Conc. name": "TNRDC",
    "Latitude": 12.9564,
    "Longitude": 80.2412
  },
  {
    "Plaza Code": 560004,
    "Plaza Name": "Medavakkam Toll\nPlaza",
    "Conc. Type": "PF",
    "Plaza Type": "TOLL",
    "Plaza Sub Type": "STATE",
    "Sate": "Tamil Nadu",
    "City": "Chennai",
    "Conc. name": "TNRDC",
    "Latitude": 12.9179,
    "Longitude": 80.2118
  },
  {
    "Plaza Code": 560005,
    "Plaza Name": "ECRlink Road Toll\nPlaza",
    "Conc. Type": "PF",
    "Plaza Type": "TOLL",
    "Plaza Sub Type": "STATE",
    "Sate": "Tamil Nadu",
    "City": "Chennai",
    "Conc. name": "TNRDC",
    "Latitude": 12.9013,
    "Longitude": 80.2183
  },
  {
    "Plaza Code": 560006,
    "Plaza Name": "Egatur Toll Plaza",
    "Conc. Type": "PF",
    "Plaza Type": "TOLL",
    "Plaza Sub Type": "STATE",
    "Sate": "Tamil Nadu",
    "City": "Chennai",
    "Conc. name": "TNRDC",
    "Latitude": 12.8902,
    "Longitude": 80.1983
  },
  {
    "Plaza Code": 560007,
    "Plaza Name": "Uthandi",
    "Conc. Type": "PF",
    "Plaza Type": "TOLL",
    "Plaza Sub Type": "STATE",
    "Sate": "Tamil Nadu",
    "City": "Chennai",
    "Conc. name": "TNRDC\n(ECR)",
    "Latitude": 12.8616039,
    "Longitude": 80.1718917
  },
  {
    "Plaza Code": 560008,
    "Plaza Name": "Central Server plaza",
    "Conc. Type": "PF",
    "Plaza Type": "TOLL",
    "Plaza Sub Type": "STATE",
    "Sate": "Tamil Nadu",
    "City": "Chennai",
    "Conc. name": "TNRDC\n(ECR)",
    "Latitude": 12.8616039,
    "Longitude": 80.1718917
  },
  {
    "Plaza Code": 560009,
    "Plaza Name": "Anumandhai",
    "Conc. Type": "PF",
    "Plaza Type": "TOLL",
    "Plaza Sub Type": "STATE",
    "Sate": "Tamil Nadu",
    "City": "Chennai",
    "Conc. name": "TNRDC\n(ECR)",
    "Latitude": 12.1239228,
    "Longitude": 79.9107642
  },
  {
    "Plaza Code": 560010,
    "Plaza Name": "Mahabalipuram\nPlaza",
    "Conc. Type": "PF",
    "Plaza Type": "TOLL",
    "Plaza Sub Type": "STATE",
    "Sate": "Tamil Nadu",
    "City": "Chennai",
    "Conc. name": "TNRDC\n(ECR)",
    "Latitude": 12.6153657,
    "Longitude": 80.0998102
  },
  {
    "Plaza Code": 560012,
    "Plaza Name": "Chinthamani Toll\nPlaza",
    "Conc. Type": "Conc.",
    "Plaza Type": "TOLL",
    "Plaza Sub Type": "STATE",
    "Sate": "Tamil Nadu",
    "City": "Madurai",
    "Conc. name": "SRI\nBALAJI\nTOLLWAY\nS",
    "Latitude": 9.8767572,
    "Longitude": 78.1349936
  },
  {
    "Plaza Code": 560013,
    "Plaza Name": "Valayangulam Toll\nPlaza",
    "Conc. Type": "Conc.",
    "Plaza Type": "TOLL",
    "Plaza Sub Type": "STATE",
    "Sate": "Tamil Nadu",
    "City": "Madurai",
    "Conc. name": "SRI\nBALAJI\nTOLLWAY\nS",
    "Latitude": 9.8266107,
    "Longitude": 78.0823004
  },
  {
    "Plaza Code": 560014,
    "Plaza Name": "Kolappancheri",
    "Conc. Type": "PF",
    "Plaza Type": "TOLL",
    "Plaza Sub Type": "STATE",
    "Sate": "Tamil Nadu",
    "City": "Chennai",
    "Conc. name": "TNRDC",
    "Latitude": 13.070524,
    "Longitude": 80.071587
  },
  {
    "Plaza Code": 560015,
    "Plaza Name": "Varadharajapuram\nToll plaza",
    "Conc. Type": "PF",
    "Plaza Type": "TOLL",
    "Plaza Sub Type": "STATE",
    "Sate": "Tamil Nadu",
    "City": "Chennai",
    "Conc. name": "TNRDC",
    "Latitude": 12.9300926,
    "Longitude": 80.0799475
  },
  {
    "Plaza Code": 560016,
    "Plaza Name": "Palavedu",
    "Conc. Type": "PF",
    "Plaza Type": "TOLL",
    "Plaza Sub Type": "STATE",
    "Sate": "Tamil Nadu",
    "City": "Chennai",
    "Conc. name": "TNRDC",
    "Latitude": 13.140047,
    "Longitude": 80.0530363
  },
  {
    "Plaza Code": 560017,
    "Plaza Name": "Chinnamullaivoyal",
    "Conc. Type": "PF",
    "Plaza Type": "TOLL",
    "Plaza Sub Type": "STATE",
    "Sate": "Tamil Nadu",
    "City": "Chennai",
    "Conc. name": "TNRDC",
    "Latitude": 13.253075,
    "Longitude": 80.2387214
  }
]